Workbook

Sheet Matriz
J1: Articulacion | W1: Regulada
A2: LINEA | B2: CONSECUTIVO | C2: OBSERVACIONES | D2: MARCA | E2: MODELO | F2: SERIAL | G2: CANTIDAD | H2: COSTO UNITARIO | I2: OTROSCOSTOS | J2: 3425230 ASISTENCIA ADMINISTRATIVA | K2: 3425227 ASISTENCIA ADMINISTRATIVA | L2: 3425495 ASISTENCIA ADMINISTRATIVA | M2: 3425231 CONTABILIZACION DE OPERACIONES COMERCIALES Y FINANCIERAS | N2: 3425503 CONTABILIZACION DE OPERACIONES COMERCIALES Y FINANCIERAS | O2: 3425505 CONTABILIZACION DE OPERACIONES COMERCIALES Y FINANCIERAS | P2: 3425511 VENTA DE PRODUCTOS EN LINEA | Q2: 3425209 CONSERVACION DE RECURSOS NATURALES | R2: 3425210 CONSERVACION DE RECURSOS NATURALES | S2: 3425504 CONSERVACION DE RECURSOS NATURALES | T2: 3425222 MONITOREO AMBIENTAL | U2: TOTAL SALIDA ARTICULACIÓN | V2: FILA ARTICULACIÓN (ref.) | W2: 3409954 ASISTENCIA EN ORGANIZACION DE ARCHIVOS . | X2: 3554431 ASISTENCIA EN ORGANIZACION DE ARCHIVOS . | Y2: 3225901 GESTIÓN ADMINISTRATIVA | Z2: 3387728 GESTIÓN ADMINISTRATIVA | AA2: 3409966 GESTIÓN ADMINISTRATIVA | AB2: 3488746 GESTIÓN ADMINISTRATIVA | AC2: 3518069 GESTIÓN ADMINISTRATIVA | AD2: 3276454 GESTIÓN EMPRESARIAL | AE2: 3404023 ASISTENCIA ADMINISTRATIVA . | AF2: 3453974 ASISTENCIA ADMINISTRATIVA . | AG2: 3485255 COORDINACION EN SISTEMAS INTEGRADOS DE GESTION | AH2: 3488730 OPERACIONES DE COMERCIO EXTERIOR | AI2: 3269063 GESTION CONTABLE Y DE INFORMACION FINANCIERA | AJ2: 3279088 GESTION CONTABLE Y DE INFORMACION FINANCIERA | AK2: 3387727 GESTION CONTABLE Y DE INFORMACION FINANCIERA | AL2: 3407377 GESTION CONTABLE Y DE INFORMACION FINANCIERA | AM2: 3409967 GESTION CONTABLE Y DE INFORMACION FINANCIERA | AN2: 3488739 GESTION CONTABLE Y DE INFORMACION FINANCIERA | AO2: 3311563 APOYO ADMINISTRATIVO EN SALUD. | AP2: 3488725 APOYO ADMINISTRATIVO EN SALUD. | AQ2: 3409965 ATENCION INTEGRAL A LA PRIMERA INFANCIA | AR2: 3529543 ATENCION INTEGRAL A LA PRIMERA INFANCIA | AS2: 3311550 ENFERMERIA. | AT2: 3488712 ENFERMERIA. | AU2: 3423692 PROMOTOR DE SALUD | AV2: 3444274 PROMOTOR DE SALUD | AW2: 3447193 INTERPRETACION DE INSTRUMENTOS MUSICALES. | AX2: Total salida Regulada | AY2: Saldo
A3: 27 | B3: 250071 | C3: Banderín festón de alta calidad material tela resistente a exteriores, color: surtido, blanco-Verde. Paquete de 7 metros por 2 unidades. | D3: NA | E3: NA | F3: NA | G3: 7 | H3: 29411.76 | I3: 0 | J3: {=IF($V3="","",IFERROR(INDEX(Articulacion!G:G,$V3),0))} | K3: {=IF($V3="","",IFERROR(INDEX(Articulacion!H:H,$V3),0))} | L3: {=IF($V3="","",IFERROR(INDEX(Articulacion!I:I,$V3),0))} | M3: {=IF($V3="","",IFERROR(INDEX(Articulacion!J:J,$V3),0))} | N3: {=IF($V3="","",IFERROR(INDEX(Articulacion!K:K,$V3),0))} | O3: {=IF($V3="","",IFERROR(INDEX(Articulacion!L:L,$V3),0))} | P3: {=IF($V3="","",IFERROR(INDEX(Articulacion!M:M,$V3),0))} | Q3: {=IF($V3="","",IFERROR(INDEX(Articulacion!N:N,$V3),0))} | R3: {=IF($V3="","",IFERROR(INDEX(Articulacion!O:O,$V3),0))} | S3: {=IF($V3="","",IFERROR(INDEX(Articulacion!P:P,$V3),0))} | T3: {=IF($V3="","",IFERROR(INDEX(Articulacion!Q:Q,$V3),0))} | U3: =IF($V3="",0,SUM(J3:T3)) -> 0 | AQ3: 3 | AR3: 4 | AX3: =SUM(W3:AW3) -> 7 | AY3: =G3-U3-AX3 -> 0
A4: 84 | B4: 292251 | C4: BANDERITAS, X5, COLORES, 1.2X4.5CM X125HJS | D4: NA | E4: NA | F4: NA | G4: 17 | H4: 4621.85 | I4: 0 | J4: {=IF($V4="","",IFERROR(INDEX(Articulacion!G:G,$V4),0))} | K4: {=IF($V4="","",IFERROR(INDEX(Articulacion!H:H,$V4),0))} | L4: {=IF($V4="","",IFERROR(INDEX(Articulacion!I:I,$V4),0))} | M4: {=IF($V4="","",IFERROR(INDEX(Articulacion!J:J,$V4),0))} | N4: {=IF($V4="","",IFERROR(INDEX(Articulacion!K:K,$V4),0))} | O4: {=IF($V4="","",IFERROR(INDEX(Articulacion!L:L,$V4),0))} | P4: {=IF($V4="","",IFERROR(INDEX(Articulacion!M:M,$V4),0))} | Q4: {=IF($V4="","",IFERROR(INDEX(Articulacion!N:N,$V4),0))} | R4: {=IF($V4="","",IFERROR(INDEX(Articulacion!O:O,$V4),0))} | S4: {=IF($V4="","",IFERROR(INDEX(Articulacion!P:P,$V4),0))} | T4: {=IF($V4="","",IFERROR(INDEX(Articulacion!Q:Q,$V4),0))} | U4: =IF($V4="",0,SUM(J4:T4)) -> 0 | AG4: 1 | AH4: 1 | AI4: 1 | AJ4: 1 | AK4: 1 | AL4: 1 | AM4: 1 | AN4: 2 | AO4: 1 | AP4: 1 | AQ4: 1 | AR4: 1 | AS4: 1 | AT4: 1 | AU4: 1 | AV4: 1 | AX4: =SUM(W4:AW4) -> 17 | AY4: =G4-U4-AX4 -> 0
A5: 83 | B5: 292165 | C5: Barra Silicona Delgada X 50 | D5: NA | E5: NA | F5: NA | G5: 3 | H5: 1680.67 | I5: 0 | J5: {=IF($V5="","",IFERROR(INDEX(Articulacion!G:G,$V5),0))} | K5: {=IF($V5="","",IFERROR(INDEX(Articulacion!H:H,$V5),0))} | L5: {=IF($V5="","",IFERROR(INDEX(Articulacion!I:I,$V5),0))} | M5: {=IF($V5="","",IFERROR(INDEX(Articulacion!J:J,$V5),0))} | N5: {=IF($V5="","",IFERROR(INDEX(Articulacion!K:K,$V5),0))} | O5: {=IF($V5="","",IFERROR(INDEX(Articulacion!L:L,$V5),0))} | P5: {=IF($V5="","",IFERROR(INDEX(Articulacion!M:M,$V5),0))} | Q5: {=IF($V5="","",IFERROR(INDEX(Articulacion!N:N,$V5),0))} | R5: {=IF($V5="","",IFERROR(INDEX(Articulacion!O:O,$V5),0))} | S5: {=IF($V5="","",IFERROR(INDEX(Articulacion!P:P,$V5),0))} | T5: {=IF($V5="","",IFERROR(INDEX(Articulacion!Q:Q,$V5),0))} | U5: =IF($V5="",0,SUM(J5:T5)) -> 0 | AB5: 1 | AC5: 1 | AD5: 1 | AX5: =SUM(W5:AW5) -> 3 | AY5: =G5-U5-AX5 -> 0
A6: 82 | B6: 249127 | C6: Barras de pegante libres de ácido. Pegante Barra 40 Gr | D6: NA | E6: NA | F6: NA | G6: 12 | H6: 10084.03 | I6: 0 | J6: {=IF($V6="","",IFERROR(INDEX(Articulacion!G:G,$V6),0))} | K6: {=IF($V6="","",IFERROR(INDEX(Articulacion!H:H,$V6),0))} | L6: {=IF($V6="","",IFERROR(INDEX(Articulacion!I:I,$V6),0))} | M6: {=IF($V6="","",IFERROR(INDEX(Articulacion!J:J,$V6),0))} | N6: {=IF($V6="","",IFERROR(INDEX(Articulacion!K:K,$V6),0))} | O6: {=IF($V6="","",IFERROR(INDEX(Articulacion!L:L,$V6),0))} | P6: {=IF($V6="","",IFERROR(INDEX(Articulacion!M:M,$V6),0))} | Q6: {=IF($V6="","",IFERROR(INDEX(Articulacion!N:N,$V6),0))} | R6: {=IF($V6="","",IFERROR(INDEX(Articulacion!O:O,$V6),0))} | S6: {=IF($V6="","",IFERROR(INDEX(Articulacion!P:P,$V6),0))} | T6: {=IF($V6="","",IFERROR(INDEX(Articulacion!Q:Q,$V6),0))} | U6: =IF($V6="",0,SUM(J6:T6)) -> 0 | AM6: 1 | AN6: 2 | AO6: 1 | AP6: 1 | AQ6: 1 | AR6: 1 | AS6: 1 | AT6: 1 | AU6: 1 | AV6: 1 | AW6: 1 | AX6: =SUM(W6:AW6) -> 12 | AY6: =G6-U6-AX6 -> 0
A7: 19 | B7: 290543 | C7: Barras de pegante sólido, composición: Adhesivo sintético libre de ácido (acid-free), no tóxico, barra en tubo plástico con mecanismo giratorio, contenido por barra: Entre 8 g y 12 g, material del envase plástico resistente con tapa de seguridad, secado rápido, limpio y sin residuos. Apto para papel, cartulina, cartón delgado y materiales escolares. Apto para uso escolar. Presentación individual | D7: NA | E7: NA | F7: NA | G7: 10 | H7: 5042.02 | I7: 0 | J7: {=IF($V7="","",IFERROR(INDEX(Articulacion!G:G,$V7),0))} | K7: {=IF($V7="","",IFERROR(INDEX(Articulacion!H:H,$V7),0))} | L7: {=IF($V7="","",IFERROR(INDEX(Articulacion!I:I,$V7),0))} | M7: {=IF($V7="","",IFERROR(INDEX(Articulacion!J:J,$V7),0))} | N7: {=IF($V7="","",IFERROR(INDEX(Articulacion!K:K,$V7),0))} | O7: {=IF($V7="","",IFERROR(INDEX(Articulacion!L:L,$V7),0))} | P7: {=IF($V7="","",IFERROR(INDEX(Articulacion!M:M,$V7),0))} | Q7: {=IF($V7="","",IFERROR(INDEX(Articulacion!N:N,$V7),0))} | R7: {=IF($V7="","",IFERROR(INDEX(Articulacion!O:O,$V7),0))} | S7: {=IF($V7="","",IFERROR(INDEX(Articulacion!P:P,$V7),0))} | T7: {=IF($V7="","",IFERROR(INDEX(Articulacion!Q:Q,$V7),0))} | U7: =IF($V7="",0,SUM(J7:T7)) -> 0 | AN7: 1 | AO7: 1 | AP7: 1 | AQ7: 1 | AR7: 1 | AS7: 1 | AT7: 1 | AU7: 1 | AV7: 1 | AW7: 1 | AX7: =SUM(W7:AW7) -> 10 | AY7: =G7-U7-AX7 -> 0
A8: 81 | B8: 290628 | C8: Billetes y monedas didácticos pesos colombianos, impresos a color por ambos lados denominaciones $ 1000, $2000, $5000, $10.000, $20.000, $50.000 y $100.000. Medidas aproximadas 12 cm x 7 cm. Incluye 94 unidades de billetes surtidos y 80 unidades de monedas de cartón surtidas. | D8: NA | E8: NA | F8: NA | G8: 20 | H8: 10084.03 | I8: 0 | J8: {=IF($V8="","",IFERROR(INDEX(Articulacion!G:G,$V8),0))} -> 0 | K8: {=IF($V8="","",IFERROR(INDEX(Articulacion!H:H,$V8),0))} -> 0 | L8: {=IF($V8="","",IFERROR(INDEX(Articulacion!I:I,$V8),0))} -> 0 | M8: {=IF($V8="","",IFERROR(INDEX(Articulacion!J:J,$V8),0))} -> 2 | N8: {=IF($V8="","",IFERROR(INDEX(Articulacion!K:K,$V8),0))} -> 2 | O8: {=IF($V8="","",IFERROR(INDEX(Articulacion!L:L,$V8),0))} -> 2 | P8: {=IF($V8="","",IFERROR(INDEX(Articulacion!M:M,$V8),0))} -> 2 | Q8: {=IF($V8="","",IFERROR(INDEX(Articulacion!N:N,$V8),0))} -> 0 | R8: {=IF($V8="","",IFERROR(INDEX(Articulacion!O:O,$V8),0))} -> 0 | S8: {=IF($V8="","",IFERROR(INDEX(Articulacion!P:P,$V8),0))} -> 0 | T8: {=IF($V8="","",IFERROR(INDEX(Articulacion!Q:Q,$V8),0))} -> 0 | U8: =IF($V8="",0,SUM(J8:T8)) -> 8 | V8: 2 | Y8: 1 | Z8: 1 | AA8: 1 | AB8: 1 | AC8: 1 | AD8: 1 | AE8: 1 | AF8: 1 | AG8: 1 | AH8: 1 | AI8: 1 | AJ8: 1 | AX8: =SUM(W8:AW8) -> 12 | AY8: =G8-U8-AX8 -> 0
A9: 80 | B9: 275696 | C9: Bisturí material del mango plástico, cuchilla en acero inoxidable, medida de cuchilla es de 18 mm con traba de seguridad. | D9: NA | E9: NA | F9: NA | G9: 10 | H9: 13445.38 | I9: 0 | J9: {=IF($V9="","",IFERROR(INDEX(Articulacion!G:G,$V9),0))} | K9: {=IF($V9="","",IFERROR(INDEX(Articulacion!H:H,$V9),0))} | L9: {=IF($V9="","",IFERROR(INDEX(Articulacion!I:I,$V9),0))} | M9: {=IF($V9="","",IFERROR(INDEX(Articulacion!J:J,$V9),0))} | N9: {=IF($V9="","",IFERROR(INDEX(Articulacion!K:K,$V9),0))} | O9: {=IF($V9="","",IFERROR(INDEX(Articulacion!L:L,$V9),0))} | P9: {=IF($V9="","",IFERROR(INDEX(Articulacion!M:M,$V9),0))} | Q9: {=IF($V9="","",IFERROR(INDEX(Articulacion!N:N,$V9),0))} | R9: {=IF($V9="","",IFERROR(INDEX(Articulacion!O:O,$V9),0))} | S9: {=IF($V9="","",IFERROR(INDEX(Articulacion!P:P,$V9),0))} | T9: {=IF($V9="","",IFERROR(INDEX(Articulacion!Q:Q,$V9),0))} | U9: =IF($V9="",0,SUM(J9:T9)) -> 0 | W9: 1 | X9: 1 | Y9: 1 | Z9: 1 | AA9: 1 | AB9: 1 | AC9: 1 | AD9: 1 | AE9: 1 | AF9: 1 | AX9: =SUM(W9:AW9) -> 10 | AY9: =G9-U9-AX9 -> 0
A10: 79 | B10: 298522 | C10: Block cuadriculado 1/8. Block de papel cuadriculado tamaño oficio X 80 hojas | D10: NA | E10: NA | F10: NA | G10: 12 | H10: 11764.71 | I10: 0 | J10: {=IF($V10="","",IFERROR(INDEX(Articulacion!G:G,$V10),0))} | K10: {=IF($V10="","",IFERROR(INDEX(Articulacion!H:H,$V10),0))} | L10: {=IF($V10="","",IFERROR(INDEX(Articulacion!I:I,$V10),0))} | M10: {=IF($V10="","",IFERROR(INDEX(Articulacion!J:J,$V10),0))} | N10: {=IF($V10="","",IFERROR(INDEX(Articulacion!K:K,$V10),0))} | O10: {=IF($V10="","",IFERROR(INDEX(Articulacion!L:L,$V10),0))} | P10: {=IF($V10="","",IFERROR(INDEX(Articulacion!M:M,$V10),0))} | Q10: {=IF($V10="","",IFERROR(INDEX(Articulacion!N:N,$V10),0))} | R10: {=IF($V10="","",IFERROR(INDEX(Articulacion!O:O,$V10),0))} | S10: {=IF($V10="","",IFERROR(INDEX(Articulacion!P:P,$V10),0))} | T10: {=IF($V10="","",IFERROR(INDEX(Articulacion!Q:Q,$V10),0))} | U10: =IF($V10="",0,SUM(J10:T10)) -> 0 | AG10: 1 | AH10: 1 | AI10: 1 | AJ10: 1 | AK10: 1 | AL10: 1 | AM10: 1 | AN10: 2 | AO10: 1 | AP10: 1 | AQ10: 1 | AX10: =SUM(W10:AW10) -> 12 | AY10: =G10-U10-AX10 -> 0
A11: 78 | B11: 239037 | C11: Block papel Iris tamaño, oficio X 30 hojas | D11: NA | E11: NA | F11: NA | G11: 18 | H11: 10924.37 | I11: 0 | J11: {=IF($V11="","",IFERROR(INDEX(Articulacion!G:G,$V11),0))} | K11: {=IF($V11="","",IFERROR(INDEX(Articulacion!H:H,$V11),0))} | L11: {=IF($V11="","",IFERROR(INDEX(Articulacion!I:I,$V11),0))} | M11: {=IF($V11="","",IFERROR(INDEX(Articulacion!J:J,$V11),0))} | N11: {=IF($V11="","",IFERROR(INDEX(Articulacion!K:K,$V11),0))} | O11: {=IF($V11="","",IFERROR(INDEX(Articulacion!L:L,$V11),0))} | P11: {=IF($V11="","",IFERROR(INDEX(Articulacion!M:M,$V11),0))} | Q11: {=IF($V11="","",IFERROR(INDEX(Articulacion!N:N,$V11),0))} | R11: {=IF($V11="","",IFERROR(INDEX(Articulacion!O:O,$V11),0))} | S11: {=IF($V11="","",IFERROR(INDEX(Articulacion!P:P,$V11),0))} | T11: {=IF($V11="","",IFERROR(INDEX(Articulacion!Q:Q,$V11),0))} | U11: =IF($V11="",0,SUM(J11:T11)) -> 0 | W11: 1 | X11: 1 | Y11: 1 | Z11: 1 | AA11: 1 | AB11: 1 | AC11: 1 | AD11: 1 | AE11: 1 | AF11: 1 | AG11: 1 | AH11: 1 | AI11: 1 | AJ11: 1 | AK11: 1 | AL11: 1 | AM11: 1 | AN11: 1 | AX11: =SUM(W11:AW11) -> 18 | AY11: =G11-U11-AX11 -> 0
A12: 32 | B12: 274294 | C12: Bolígrafo de punta fina o media, Color de tinta: Morado, base de aceite o gel de secado rápido, no tóxica, Punta media: 1.0 mm y/o Punta fina: 0.7 mm. cuerpo: Plástico resistente, ergonómico, con clip para sujeción, con tapa de seguridad o mecanismo retráctil, flujo de tinta continuo, uniforme y sin saltos. Caja por 12 unidades | D12: NA | E12: NA | F12: NA | G12: 2 | H12: 35294.12 | I12: 0 | J12: {=IF($V12="","",IFERROR(INDEX(Articulacion!G:G,$V12),0))} | K12: {=IF($V12="","",IFERROR(INDEX(Articulacion!H:H,$V12),0))} | L12: {=IF($V12="","",IFERROR(INDEX(Articulacion!I:I,$V12),0))} | M12: {=IF($V12="","",IFERROR(INDEX(Articulacion!J:J,$V12),0))} | N12: {=IF($V12="","",IFERROR(INDEX(Articulacion!K:K,$V12),0))} | O12: {=IF($V12="","",IFERROR(INDEX(Articulacion!L:L,$V12),0))} | P12: {=IF($V12="","",IFERROR(INDEX(Articulacion!M:M,$V12),0))} | Q12: {=IF($V12="","",IFERROR(INDEX(Articulacion!N:N,$V12),0))} | R12: {=IF($V12="","",IFERROR(INDEX(Articulacion!O:O,$V12),0))} | S12: {=IF($V12="","",IFERROR(INDEX(Articulacion!P:P,$V12),0))} | T12: {=IF($V12="","",IFERROR(INDEX(Articulacion!Q:Q,$V12),0))} | U12: =IF($V12="",0,SUM(J12:T12)) -> 0 | Y12: 1 | Z12: 1 | AX12: =SUM(W12:AW12) -> 2 | AY12: =G12-U12-AX12 -> 0
A13: 77 | B13: 292235 | C13: BOLÍGRAFO NEGRO, caja por 12 unidades, barril triangular transparente, punta de 1.0 mm (o 0.7 mm fino) y sistema de tinta InkJoy, secado rápido, tapa con clip y tinta negra intensa. | D13: NA | E13: NA | F13: NA | G13: 18 | H13: 10084.03 | I13: 0 | J13: {=IF($V13="","",IFERROR(INDEX(Articulacion!G:G,$V13),0))} | K13: {=IF($V13="","",IFERROR(INDEX(Articulacion!H:H,$V13),0))} | L13: {=IF($V13="","",IFERROR(INDEX(Articulacion!I:I,$V13),0))} | M13: {=IF($V13="","",IFERROR(INDEX(Articulacion!J:J,$V13),0))} | N13: {=IF($V13="","",IFERROR(INDEX(Articulacion!K:K,$V13),0))} | O13: {=IF($V13="","",IFERROR(INDEX(Articulacion!L:L,$V13),0))} | P13: {=IF($V13="","",IFERROR(INDEX(Articulacion!M:M,$V13),0))} | Q13: {=IF($V13="","",IFERROR(INDEX(Articulacion!N:N,$V13),0))} | R13: {=IF($V13="","",IFERROR(INDEX(Articulacion!O:O,$V13),0))} | S13: {=IF($V13="","",IFERROR(INDEX(Articulacion!P:P,$V13),0))} | T13: {=IF($V13="","",IFERROR(INDEX(Articulacion!Q:Q,$V13),0))} | U13: =IF($V13="",0,SUM(J13:T13)) -> 0 | AG13: 1 | AH13: 1 | AI13: 1 | AJ13: 1 | AK13: 1 | AL13: 1 | AM13: 1 | AN13: 2 | AO13: 1 | AP13: 1 | AQ13: 1 | AR13: 1 | AS13: 1 | AT13: 1 | AU13: 1 | AV13: 1 | AW13: 1 | AX13: =SUM(W13:AW13) -> 18 | AY13: =G13-U13-AX13 -> 0
A14: 76 | B14: 244261 | C14: Borrador para tablero acrílico, en madera o plástico | D14: NA | E14: NA | F14: NA | G14: 15 | H14: 4621.85 | I14: 0 | J14: {=IF($V14="","",IFERROR(INDEX(Articulacion!G:G,$V14),0))} | K14: {=IF($V14="","",IFERROR(INDEX(Articulacion!H:H,$V14),0))} | L14: {=IF($V14="","",IFERROR(INDEX(Articulacion!I:I,$V14),0))} | M14: {=IF($V14="","",IFERROR(INDEX(Articulacion!J:J,$V14),0))} | N14: {=IF($V14="","",IFERROR(INDEX(Articulacion!K:K,$V14),0))} | O14: {=IF($V14="","",IFERROR(INDEX(Articulacion!L:L,$V14),0))} | P14: {=IF($V14="","",IFERROR(INDEX(Articulacion!M:M,$V14),0))} | Q14: {=IF($V14="","",IFERROR(INDEX(Articulacion!N:N,$V14),0))} | R14: {=IF($V14="","",IFERROR(INDEX(Articulacion!O:O,$V14),0))} | S14: {=IF($V14="","",IFERROR(INDEX(Articulacion!P:P,$V14),0))} | T14: {=IF($V14="","",IFERROR(INDEX(Articulacion!Q:Q,$V14),0))} | U14: =IF($V14="",0,SUM(J14:T14)) -> 0 | W14: 1 | X14: 1 | Y14: 1 | Z14: 1 | AA14: 1 | AB14: 1 | AC14: 1 | AD14: 1 | AE14: 1 | AF14: 1 | AG14: 1 | AH14: 1 | AI14: 1 | AJ14: 1 | AK14: 1 | AX14: =SUM(W14:AW14) -> 15 | AY14: =G14-U14-AX14 -> 0
A15: 92 | B15: 292245 | C15: Caja para archivo tipo troquelada x 100 en cartón corrugado tipo nevera reglamentaria en cartón C 650, tamaño: alto 40 cm, ancho 10.5 cm, largo 26 cm, rotulada, sistema doble ventilación | D15: NA | E15: NA | F15: NA | G15: 20 | H15: 14285.71 | I15: 0 | J15: {=IF($V15="","",IFERROR(INDEX(Articulacion!G:G,$V15),0))} | K15: {=IF($V15="","",IFERROR(INDEX(Articulacion!H:H,$V15),0))} | L15: {=IF($V15="","",IFERROR(INDEX(Articulacion!I:I,$V15),0))} | M15: {=IF($V15="","",IFERROR(INDEX(Articulacion!J:J,$V15),0))} | N15: {=IF($V15="","",IFERROR(INDEX(Articulacion!K:K,$V15),0))} | O15: {=IF($V15="","",IFERROR(INDEX(Articulacion!L:L,$V15),0))} | P15: {=IF($V15="","",IFERROR(INDEX(Articulacion!M:M,$V15),0))} | Q15: {=IF($V15="","",IFERROR(INDEX(Articulacion!N:N,$V15),0))} | R15: {=IF($V15="","",IFERROR(INDEX(Articulacion!O:O,$V15),0))} | S15: {=IF($V15="","",IFERROR(INDEX(Articulacion!P:P,$V15),0))} | T15: {=IF($V15="","",IFERROR(INDEX(Articulacion!Q:Q,$V15),0))} | U15: =IF($V15="",0,SUM(J15:T15)) -> 0 | W15: 5 | X15: 5 | Y15: 2 | Z15: 2 | AA15: 1 | AB15: 1 | AC15: 1 | AD15: 1 | AE15: 1 | AF15: 1 | AX15: =SUM(W15:AW15) -> 20 | AY15: =G15-U15-AX15 -> 0
A16: 91 | B16: 298052 | C16: Caja para archivo tipo troquelada X 300, resistente, abertura para sujetar y transportar con facilidad, cartón nuevo calibre 720, color Kraft, sistema ideal para evitar que se deforme o se desfonde caja con tapa. Medidas: Alto 26 Centímetro, largo 40 Centímetro. Ancho 30 centímetros. | D16: NA | E16: NA | F16: NA | G16: 20 | H16: 15966.39 | I16: 0 | J16: {=IF($V16="","",IFERROR(INDEX(Articulacion!G:G,$V16),0))} | K16: {=IF($V16="","",IFERROR(INDEX(Articulacion!H:H,$V16),0))} | L16: {=IF($V16="","",IFERROR(INDEX(Articulacion!I:I,$V16),0))} | M16: {=IF($V16="","",IFERROR(INDEX(Articulacion!J:J,$V16),0))} | N16: {=IF($V16="","",IFERROR(INDEX(Articulacion!K:K,$V16),0))} | O16: {=IF($V16="","",IFERROR(INDEX(Articulacion!L:L,$V16),0))} | P16: {=IF($V16="","",IFERROR(INDEX(Articulacion!M:M,$V16),0))} | Q16: {=IF($V16="","",IFERROR(INDEX(Articulacion!N:N,$V16),0))} | R16: {=IF($V16="","",IFERROR(INDEX(Articulacion!O:O,$V16),0))} | S16: {=IF($V16="","",IFERROR(INDEX(Articulacion!P:P,$V16),0))} | T16: {=IF($V16="","",IFERROR(INDEX(Articulacion!Q:Q,$V16),0))} | U16: =IF($V16="",0,SUM(J16:T16)) -> 0 | W16: 10 | X16: 10 | AX16: =SUM(W16:AW16) -> 20 | AY16: =G16-U16-AX16 -> 0
A17: 75 | B17: 275468 | C17: CAJA PARA ARCHIVOS CENTRAL ref: x-200, ref: x-200, rótulo externo de identificación material de construcción: cartón corrugado de pared sencilla con recubrimiento interno especificaciones técnicas, resistencia a la compresión vertical el cartón corrugado debe tener una resistencia a la compresión vertical (rcv) de 790 930 kgf/m | D17: NA | E17: NA | F17: NA | G17: 12 | H17: 7983.19 | I17: 0 | J17: {=IF($V17="","",IFERROR(INDEX(Articulacion!G:G,$V17),0))} | K17: {=IF($V17="","",IFERROR(INDEX(Articulacion!H:H,$V17),0))} | L17: {=IF($V17="","",IFERROR(INDEX(Articulacion!I:I,$V17),0))} | M17: {=IF($V17="","",IFERROR(INDEX(Articulacion!J:J,$V17),0))} | N17: {=IF($V17="","",IFERROR(INDEX(Articulacion!K:K,$V17),0))} | O17: {=IF($V17="","",IFERROR(INDEX(Articulacion!L:L,$V17),0))} | P17: {=IF($V17="","",IFERROR(INDEX(Articulacion!M:M,$V17),0))} | Q17: {=IF($V17="","",IFERROR(INDEX(Articulacion!N:N,$V17),0))} | R17: {=IF($V17="","",IFERROR(INDEX(Articulacion!O:O,$V17),0))} | S17: {=IF($V17="","",IFERROR(INDEX(Articulacion!P:P,$V17),0))} | T17: {=IF($V17="","",IFERROR(INDEX(Articulacion!Q:Q,$V17),0))} | U17: =IF($V17="",0,SUM(J17:T17)) -> 0 | W17: 6 | X17: 6 | AX17: =SUM(W17:AW17) -> 12 | AY17: =G17-U17-AX17 -> 0
A18: 93 | B18: 292167 | C18: Carpeta archivo 2 tapas con refuerzo, Juego de tapas archivo yute, refuerzo tela tamaño oficio, largo 26 centímetros, ancho 37 centímetros, espesor 1 milímetro, normativa del archivo general, entidades públicas y privadas, incluye tapa y contratapa con aleta vertical. Contratapa larga 39 centímetros (37 centímetros más 2 centímetros de aleta; ancho 26 centímetros.) | D18: NA | E18: NA | F18: NA | G18: 30 | H18: 10924.37 | I18: 0 | J18: {=IF($V18="","",IFERROR(INDEX(Articulacion!G:G,$V18),0))} | K18: {=IF($V18="","",IFERROR(INDEX(Articulacion!H:H,$V18),0))} | L18: {=IF($V18="","",IFERROR(INDEX(Articulacion!I:I,$V18),0))} | M18: {=IF($V18="","",IFERROR(INDEX(Articulacion!J:J,$V18),0))} | N18: {=IF($V18="","",IFERROR(INDEX(Articulacion!K:K,$V18),0))} | O18: {=IF($V18="","",IFERROR(INDEX(Articulacion!L:L,$V18),0))} | P18: {=IF($V18="","",IFERROR(INDEX(Articulacion!M:M,$V18),0))} | Q18: {=IF($V18="","",IFERROR(INDEX(Articulacion!N:N,$V18),0))} | R18: {=IF($V18="","",IFERROR(INDEX(Articulacion!O:O,$V18),0))} | S18: {=IF($V18="","",IFERROR(INDEX(Articulacion!P:P,$V18),0))} | T18: {=IF($V18="","",IFERROR(INDEX(Articulacion!Q:Q,$V18),0))} | U18: =IF($V18="",0,SUM(J18:T18)) -> 0 | W18: 2 | X18: 2 | Y18: 1 | Z18: 1 | AA18: 1 | AB18: 1 | AC18: 1 | AD18: 1 | AE18: 1 | AF18: 1 | AG18: 1 | AH18: 1 | AI18: 1 | AJ18: 1 | AK18: 1 | AL18: 1 | AM18: 1 | AN18: 2 | AO18: 1 | AP18: 1 | AQ18: 1 | AR18: 1 | AS18: 1 | AT18: 1 | AU18: 1 | AV18: 1 | AW18: 1 | AX18: =SUM(W18:AW18) -> 30 | AY18: =G18-U18-AX18 -> 0
A19: 74 | B19: 272123 | C19: Carpeta Blanca cuatro (4) aletas, Con una cubierta anterior y una posterior con solapas laterales que doblan al interior. Incluye grafado para 4 pliegues sobre cada solapa. La distancia entre los pliegues es de 1 cm., para obtener diferentes capacidades de almacenamiento. Debe tener un acabado liso, suave, libre de partículas abrasivas u otras imperfecciones. Se recomienda el uso de propalcote desacidificada de mínimo 240 g/m2 o de propalcote de 300 g/m2 o 320 g/m2. Y que cumplan con las siguientes dimensiones., Solapas laterales: (4 aletas) Gramaje 320 Gr. Medidas: Ancho en totalidad 69.5 cm X largo 69,5 cm Base central: ancho 22 Cm X largo 37 cm Base aletas laterales: ancho 25 Cm X largo 35 cm. Base aletas superiores: ancho 22 Cm X largo 17 cm. Grafas (5) con capacidad de hasta 400 folios. Material: Cartulina libre de pulpas lignificadas o recicladas propalcote 320g, Rotuladas con logo del SENA y nombre del Centro (REGIONAL HUILA - Centro de Formación Agroindustrial La Angostura) 1 sola tinta. Recubrimiento: PH neutro o con reserva alcalina. | D19: NA | E19: NA | F19: NA | G19: 87 | H19: 4621.85 | I19: 0 | J19: {=IF($V19="","",IFERROR(INDEX(Articulacion!G:G,$V19),0))} -> 1 | K19: {=IF($V19="","",IFERROR(INDEX(Articulacion!H:H,$V19),0))} -> 1 | L19: {=IF($V19="","",IFERROR(INDEX(Articulacion!I:I,$V19),0))} -> 1 | M19: {=IF($V19="","",IFERROR(INDEX(Articulacion!J:J,$V19),0))} -> 1 | N19: {=IF($V19="","",IFERROR(INDEX(Articulacion!K:K,$V19),0))} -> 1 | O19: {=IF($V19="","",IFERROR(INDEX(Articulacion!L:L,$V19),0))} -> 1 | P19: {=IF($V19="","",IFERROR(INDEX(Articulacion!M:M,$V19),0))} -> 1 | Q19: {=IF($V19="","",IFERROR(INDEX(Articulacion!N:N,$V19),0))} -> 0 | R19: {=IF($V19="","",IFERROR(INDEX(Articulacion!O:O,$V19),0))} -> 0 | S19: {=IF($V19="","",IFERROR(INDEX(Articulacion!P:P,$V19),0))} -> 0 | T19: {=IF($V19="","",IFERROR(INDEX(Articulacion!Q:Q,$V19),0))} -> 0 | U19: =IF($V19="",0,SUM(J19:T19)) -> 7 | V19: 3 | W19: 20 | X19: 20 | Y19: 5 | Z19: 5 | AA19: 5 | AB19: 5 | AC19: 5 | AD19: 5 | AE19: 5 | AF19: 5 | AX19: =SUM(W19:AW19) -> 80 | AY19: =G19-U19-AX19 -> 0
A20: 26 | B20: 279953 | C20: Cartelera de corcho resistente al pinchado constante, de grano puro y uniforme, funcional y durable con marco plástico blanco o verde y esquinas redondeadas, medidas: desde 1.20 x 80 | D20: NA | E20: NA | F20: NA | G20: 1 | H20: 252100.84 | I20: 0 | J20: {=IF($V20="","",IFERROR(INDEX(Articulacion!G:G,$V20),0))} | K20: {=IF($V20="","",IFERROR(INDEX(Articulacion!H:H,$V20),0))} | L20: {=IF($V20="","",IFERROR(INDEX(Articulacion!I:I,$V20),0))} | M20: {=IF($V20="","",IFERROR(INDEX(Articulacion!J:J,$V20),0))} | N20: {=IF($V20="","",IFERROR(INDEX(Articulacion!K:K,$V20),0))} | O20: {=IF($V20="","",IFERROR(INDEX(Articulacion!L:L,$V20),0))} | P20: {=IF($V20="","",IFERROR(INDEX(Articulacion!M:M,$V20),0))} | Q20: {=IF($V20="","",IFERROR(INDEX(Articulacion!N:N,$V20),0))} | R20: {=IF($V20="","",IFERROR(INDEX(Articulacion!O:O,$V20),0))} | S20: {=IF($V20="","",IFERROR(INDEX(Articulacion!P:P,$V20),0))} | T20: {=IF($V20="","",IFERROR(INDEX(Articulacion!Q:Q,$V20),0))} | U20: =IF($V20="",0,SUM(J20:T20)) -> 0 | AS20: 1 | AX20: =SUM(W20:AW20) -> 1 | AY20: =G20-U20-AX20 -> 0
A21: 71 | B21: 235926 | C21: Cartulina 1/8 colores surtidos PAQUETE X 10 UNIDADES. colores de 85cmX25cm | D21: NA | E21: NA | F21: NA | G21: 25 | H21: 4201.68 | I21: 0 | J21: {=IF($V21="","",IFERROR(INDEX(Articulacion!G:G,$V21),0))} -> 4 | K21: {=IF($V21="","",IFERROR(INDEX(Articulacion!H:H,$V21),0))} -> 4 | L21: {=IF($V21="","",IFERROR(INDEX(Articulacion!I:I,$V21),0))} -> 4 | M21: {=IF($V21="","",IFERROR(INDEX(Articulacion!J:J,$V21),0))} -> 4 | N21: {=IF($V21="","",IFERROR(INDEX(Articulacion!K:K,$V21),0))} -> 4 | O21: {=IF($V21="","",IFERROR(INDEX(Articulacion!L:L,$V21),0))} -> 3 | P21: {=IF($V21="","",IFERROR(INDEX(Articulacion!M:M,$V21),0))} -> 2 | Q21: {=IF($V21="","",IFERROR(INDEX(Articulacion!N:N,$V21),0))} -> 0 | R21: {=IF($V21="","",IFERROR(INDEX(Articulacion!O:O,$V21),0))} -> 0 | S21: {=IF($V21="","",IFERROR(INDEX(Articulacion!P:P,$V21),0))} -> 0 | T21: {=IF($V21="","",IFERROR(INDEX(Articulacion!Q:Q,$V21),0))} -> 0 | U21: =IF($V21="",0,SUM(J21:T21)) -> 25 | V21: 4 | AX21: =SUM(W21:AW21) -> 0 | AY21: =G21-U21-AX21 -> 0
A22: 72 | B22: 275471 | C22: Cartulina colores surtidos Tamaño: Pliego 70 x 100 cm. Colores surtidos | D22: NA | E22: NA | F22: NA | G22: 31 | H22: 2100.84 | I22: 0 | J22: {=IF($V22="","",IFERROR(INDEX(Articulacion!G:G,$V22),0))} | K22: {=IF($V22="","",IFERROR(INDEX(Articulacion!H:H,$V22),0))} | L22: {=IF($V22="","",IFERROR(INDEX(Articulacion!I:I,$V22),0))} | M22: {=IF($V22="","",IFERROR(INDEX(Articulacion!J:J,$V22),0))} | N22: {=IF($V22="","",IFERROR(INDEX(Articulacion!K:K,$V22),0))} | O22: {=IF($V22="","",IFERROR(INDEX(Articulacion!L:L,$V22),0))} | P22: {=IF($V22="","",IFERROR(INDEX(Articulacion!M:M,$V22),0))} | Q22: {=IF($V22="","",IFERROR(INDEX(Articulacion!N:N,$V22),0))} | R22: {=IF($V22="","",IFERROR(INDEX(Articulacion!O:O,$V22),0))} | S22: {=IF($V22="","",IFERROR(INDEX(Articulacion!P:P,$V22),0))} | T22: {=IF($V22="","",IFERROR(INDEX(Articulacion!Q:Q,$V22),0))} | U22: =IF($V22="",0,SUM(J22:T22)) -> 0 | W22: 1 | X22: 1 | Y22: 1 | Z22: 1 | AA22: 1 | AB22: 1 | AC22: 1 | AD22: 1 | AE22: 1 | AF22: 1 | AG22: 1 | AH22: 1 | AI22: 1 | AJ22: 1 | AK22: 1 | AL22: 1 | AM22: 1 | AN22: 2 | AO22: 1 | AP22: 1 | AQ22: 1 | AR22: 1 | AS22: 1 | AT22: 2 | AU22: 2 | AV22: 2 | AW22: 1 | AX22: =SUM(W22:AW22) -> 31 | AY22: =G22-U22-AX22 -> 0
A23: 73 | B23: 235926 | C23: Cartulina octavos x 100 unidades Tamaño formato octavo, equivalente a aproximadamente 22 cm x 28 cm, gramaje: Entre 150 g/m² y 180 g/m² según disponibilidad, colores surtidos, superficie lisa y uniforme, rígida, resistente y apta para escritura, impresión y manualidades. Apta para lápiz, marcador, colores, témpera, pegantes y otros materiales escolares. Presentación: Paquete por 100 unidades, empacado y sellado. | D23: NA | E23: NA | F23: NA | G23: 10 | H23: 33613.45 | I23: 0 | J23: {=IF($V23="","",IFERROR(INDEX(Articulacion!G:G,$V23),0))} | K23: {=IF($V23="","",IFERROR(INDEX(Articulacion!H:H,$V23),0))} | L23: {=IF($V23="","",IFERROR(INDEX(Articulacion!I:I,$V23),0))} | M23: {=IF($V23="","",IFERROR(INDEX(Articulacion!J:J,$V23),0))} | N23: {=IF($V23="","",IFERROR(INDEX(Articulacion!K:K,$V23),0))} | O23: {=IF($V23="","",IFERROR(INDEX(Articulacion!L:L,$V23),0))} | P23: {=IF($V23="","",IFERROR(INDEX(Articulacion!M:M,$V23),0))} | Q23: {=IF($V23="","",IFERROR(INDEX(Articulacion!N:N,$V23),0))} | R23: {=IF($V23="","",IFERROR(INDEX(Articulacion!O:O,$V23),0))} | S23: {=IF($V23="","",IFERROR(INDEX(Articulacion!P:P,$V23),0))} | T23: {=IF($V23="","",IFERROR(INDEX(Articulacion!Q:Q,$V23),0))} | U23: =IF($V23="",0,SUM(J23:T23)) -> 0 | AE23: 1 | AF23: 1 | AG23: 1 | AH23: 1 | AI23: 1 | AJ23: 1 | AK23: 1 | AL23: 1 | AM23: 1 | AN23: 1 | AX23: =SUM(W23:AW23) -> 10 | AY23: =G23-U23-AX23 -> 0
A24: 22 | B24: 280058 | C24: Cera para hojas facilita el conteo de hojas y billetes, antibacterial, humectante, no mancha, no tóxico. 20 gramos. | D24: NA | E24: NA | F24: NA | G24: 10 | H24: 7563.03 | I24: 0 | J24: {=IF($V24="","",IFERROR(INDEX(Articulacion!G:G,$V24),0))} | K24: {=IF($V24="","",IFERROR(INDEX(Articulacion!H:H,$V24),0))} | L24: {=IF($V24="","",IFERROR(INDEX(Articulacion!I:I,$V24),0))} | M24: {=IF($V24="","",IFERROR(INDEX(Articulacion!J:J,$V24),0))} | N24: {=IF($V24="","",IFERROR(INDEX(Articulacion!K:K,$V24),0))} | O24: {=IF($V24="","",IFERROR(INDEX(Articulacion!L:L,$V24),0))} | P24: {=IF($V24="","",IFERROR(INDEX(Articulacion!M:M,$V24),0))} | Q24: {=IF($V24="","",IFERROR(INDEX(Articulacion!N:N,$V24),0))} | R24: {=IF($V24="","",IFERROR(INDEX(Articulacion!O:O,$V24),0))} | S24: {=IF($V24="","",IFERROR(INDEX(Articulacion!P:P,$V24),0))} | T24: {=IF($V24="","",IFERROR(INDEX(Articulacion!Q:Q,$V24),0))} | U24: =IF($V24="",0,SUM(J24:T24)) -> 0 | W24: 5 | X24: 5 | AX24: =SUM(W24:AW24) -> 10 | AY24: =G24-U24-AX24 -> 0
A25: 70 | B25: 235764 | C25: Cinta Adhesiva transparente 45 X 40 mts ancha. | D25: NA | E25: NA | F25: NA | G25: 12 | H25: 5042.02 | I25: 0 | J25: {=IF($V25="","",IFERROR(INDEX(Articulacion!G:G,$V25),0))} | K25: {=IF($V25="","",IFERROR(INDEX(Articulacion!H:H,$V25),0))} | L25: {=IF($V25="","",IFERROR(INDEX(Articulacion!I:I,$V25),0))} | M25: {=IF($V25="","",IFERROR(INDEX(Articulacion!J:J,$V25),0))} | N25: {=IF($V25="","",IFERROR(INDEX(Articulacion!K:K,$V25),0))} | O25: {=IF($V25="","",IFERROR(INDEX(Articulacion!L:L,$V25),0))} | P25: {=IF($V25="","",IFERROR(INDEX(Articulacion!M:M,$V25),0))} | Q25: {=IF($V25="","",IFERROR(INDEX(Articulacion!N:N,$V25),0))} | R25: {=IF($V25="","",IFERROR(INDEX(Articulacion!O:O,$V25),0))} | S25: {=IF($V25="","",IFERROR(INDEX(Articulacion!P:P,$V25),0))} | T25: {=IF($V25="","",IFERROR(INDEX(Articulacion!Q:Q,$V25),0))} | U25: =IF($V25="",0,SUM(J25:T25)) -> 0 | W25: 1 | X25: 1 | Y25: 1 | Z25: 1 | AA25: 1 | AB25: 1 | AC25: 1 | AD25: 1 | AE25: 1 | AF25: 1 | AG25: 1 | AH25: 1 | AX25: =SUM(W25:AW25) -> 12 | AY25: =G25-U25-AX25 -> 0
A26: 69 | B26: 272136 | C26: Cinta de enmascarar, ancho 18mm, rollo x 40 metros | D26: NA | E26: NA | F26: NA | G26: 8 | H26: 5462.18 | I26: 0 | J26: {=IF($V26="","",IFERROR(INDEX(Articulacion!G:G,$V26),0))} | K26: {=IF($V26="","",IFERROR(INDEX(Articulacion!H:H,$V26),0))} | L26: {=IF($V26="","",IFERROR(INDEX(Articulacion!I:I,$V26),0))} | M26: {=IF($V26="","",IFERROR(INDEX(Articulacion!J:J,$V26),0))} | N26: {=IF($V26="","",IFERROR(INDEX(Articulacion!K:K,$V26),0))} | O26: {=IF($V26="","",IFERROR(INDEX(Articulacion!L:L,$V26),0))} | P26: {=IF($V26="","",IFERROR(INDEX(Articulacion!M:M,$V26),0))} | Q26: {=IF($V26="","",IFERROR(INDEX(Articulacion!N:N,$V26),0))} | R26: {=IF($V26="","",IFERROR(INDEX(Articulacion!O:O,$V26),0))} | S26: {=IF($V26="","",IFERROR(INDEX(Articulacion!P:P,$V26),0))} | T26: {=IF($V26="","",IFERROR(INDEX(Articulacion!Q:Q,$V26),0))} | U26: =IF($V26="",0,SUM(J26:T26)) -> 0 | AI26: 1 | AJ26: 1 | AK26: 1 | AL26: 1 | AM26: 1 | AN26: 2 | AO26: 1 | AX26: =SUM(W26:AW26) -> 8 | AY26: =G26-U26-AX26 -> 0
A27: 87 | B27: 237623 | C27: Cinta de tela adhesiva, superficie rotulable, para refuerzo y reparación de lomos y cubiertas, material lino libre de ácido, teñido con colores naturales, grosor 2 centímetros. | D27: NA | E27: NA | F27: NA | G27: 11 | H27: 26890.76 | I27: 0 | J27: {=IF($V27="","",IFERROR(INDEX(Articulacion!G:G,$V27),0))} | K27: {=IF($V27="","",IFERROR(INDEX(Articulacion!H:H,$V27),0))} | L27: {=IF($V27="","",IFERROR(INDEX(Articulacion!I:I,$V27),0))} | M27: {=IF($V27="","",IFERROR(INDEX(Articulacion!J:J,$V27),0))} | N27: {=IF($V27="","",IFERROR(INDEX(Articulacion!K:K,$V27),0))} | O27: {=IF($V27="","",IFERROR(INDEX(Articulacion!L:L,$V27),0))} | P27: {=IF($V27="","",IFERROR(INDEX(Articulacion!M:M,$V27),0))} | Q27: {=IF($V27="","",IFERROR(INDEX(Articulacion!N:N,$V27),0))} | R27: {=IF($V27="","",IFERROR(INDEX(Articulacion!O:O,$V27),0))} | S27: {=IF($V27="","",IFERROR(INDEX(Articulacion!P:P,$V27),0))} | T27: {=IF($V27="","",IFERROR(INDEX(Articulacion!Q:Q,$V27),0))} | U27: =IF($V27="",0,SUM(J27:T27)) -> 0 | W27: 5 | X27: 5 | Y27: 1 | AX27: =SUM(W27:AW27) -> 11 | AY27: =G27-U27-AX27 -> 0
A28: 68 | B28: 290227 | C28: Cinta doble Cara Extra Fuerte Vhb Transparente 3m 19mmx5m | D28: NA | E28: NA | F28: NA | G28: 5 | H28: 12605.04 | I28: 0 | J28: {=IF($V28="","",IFERROR(INDEX(Articulacion!G:G,$V28),0))} | K28: {=IF($V28="","",IFERROR(INDEX(Articulacion!H:H,$V28),0))} | L28: {=IF($V28="","",IFERROR(INDEX(Articulacion!I:I,$V28),0))} | M28: {=IF($V28="","",IFERROR(INDEX(Articulacion!J:J,$V28),0))} | N28: {=IF($V28="","",IFERROR(INDEX(Articulacion!K:K,$V28),0))} | O28: {=IF($V28="","",IFERROR(INDEX(Articulacion!L:L,$V28),0))} | P28: {=IF($V28="","",IFERROR(INDEX(Articulacion!M:M,$V28),0))} | Q28: {=IF($V28="","",IFERROR(INDEX(Articulacion!N:N,$V28),0))} | R28: {=IF($V28="","",IFERROR(INDEX(Articulacion!O:O,$V28),0))} | S28: {=IF($V28="","",IFERROR(INDEX(Articulacion!P:P,$V28),0))} | T28: {=IF($V28="","",IFERROR(INDEX(Articulacion!Q:Q,$V28),0))} | U28: =IF($V28="",0,SUM(J28:T28)) -> 0 | W28: 1 | X28: 1 | Y28: 1 | Z28: 1 | AA28: 1 | AX28: =SUM(W28:AW28) -> 5 | AY28: =G28-U28-AX28 -> 0
A29: 66 | B29: 292272 | C29: Clip estándar jumbo Caja X 100 unidades | D29: NA | E29: NA | F29: NA | G29: 5 | H29: 5042.02 | I29: 0 | J29: {=IF($V29="","",IFERROR(INDEX(Articulacion!G:G,$V29),0))} | K29: {=IF($V29="","",IFERROR(INDEX(Articulacion!H:H,$V29),0))} | L29: {=IF($V29="","",IFERROR(INDEX(Articulacion!I:I,$V29),0))} | M29: {=IF($V29="","",IFERROR(INDEX(Articulacion!J:J,$V29),0))} | N29: {=IF($V29="","",IFERROR(INDEX(Articulacion!K:K,$V29),0))} | O29: {=IF($V29="","",IFERROR(INDEX(Articulacion!L:L,$V29),0))} | P29: {=IF($V29="","",IFERROR(INDEX(Articulacion!M:M,$V29),0))} | Q29: {=IF($V29="","",IFERROR(INDEX(Articulacion!N:N,$V29),0))} | R29: {=IF($V29="","",IFERROR(INDEX(Articulacion!O:O,$V29),0))} | S29: {=IF($V29="","",IFERROR(INDEX(Articulacion!P:P,$V29),0))} | T29: {=IF($V29="","",IFERROR(INDEX(Articulacion!Q:Q,$V29),0))} | U29: =IF($V29="",0,SUM(J29:T29)) -> 0 | AB29: 1 | AC29: 1 | AD29: 1 | AE29: 1 | AF29: 1 | AX29: =SUM(W29:AW29) -> 5 | AY29: =G29-U29-AX29 -> 0
A30: 11 | B30: 260817 | C30: Comprobante de ingreso talonario, x, 80, hojas | D30: NA | E30: NA | F30: NA | G30: 1 | H30: 19327.73 | I30: 0 | J30: {=IF($V30="","",IFERROR(INDEX(Articulacion!G:G,$V30),0))} -> 0 | K30: {=IF($V30="","",IFERROR(INDEX(Articulacion!H:H,$V30),0))} -> 0 | L30: {=IF($V30="","",IFERROR(INDEX(Articulacion!I:I,$V30),0))} -> 0 | M30: {=IF($V30="","",IFERROR(INDEX(Articulacion!J:J,$V30),0))} -> 1 | N30: {=IF($V30="","",IFERROR(INDEX(Articulacion!K:K,$V30),0))} -> 0 | O30: {=IF($V30="","",IFERROR(INDEX(Articulacion!L:L,$V30),0))} -> 0 | P30: {=IF($V30="","",IFERROR(INDEX(Articulacion!M:M,$V30),0))} -> 0 | Q30: {=IF($V30="","",IFERROR(INDEX(Articulacion!N:N,$V30),0))} -> 0 | R30: {=IF($V30="","",IFERROR(INDEX(Articulacion!O:O,$V30),0))} -> 0 | S30: {=IF($V30="","",IFERROR(INDEX(Articulacion!P:P,$V30),0))} -> 0 | T30: {=IF($V30="","",IFERROR(INDEX(Articulacion!Q:Q,$V30),0))} -> 0 | U30: =IF($V30="",0,SUM(J30:T30)) -> 1 | V30: 11 | AX30: =SUM(W30:AW30) -> 0 | AY30: =G30-U30-AX30 -> 0
A31: 60 | B31: 278283 | C31: Cosedora Grapadora Metálica De Pinza Alicate Calidad Superior | D31: NA | E31: NA | F31: NA | G31: 5 | H31: 50420.17 | I31: 0 | J31: {=IF($V31="","",IFERROR(INDEX(Articulacion!G:G,$V31),0))} | K31: {=IF($V31="","",IFERROR(INDEX(Articulacion!H:H,$V31),0))} | L31: {=IF($V31="","",IFERROR(INDEX(Articulacion!I:I,$V31),0))} | M31: {=IF($V31="","",IFERROR(INDEX(Articulacion!J:J,$V31),0))} | N31: {=IF($V31="","",IFERROR(INDEX(Articulacion!K:K,$V31),0))} | O31: {=IF($V31="","",IFERROR(INDEX(Articulacion!L:L,$V31),0))} | P31: {=IF($V31="","",IFERROR(INDEX(Articulacion!M:M,$V31),0))} | Q31: {=IF($V31="","",IFERROR(INDEX(Articulacion!N:N,$V31),0))} | R31: {=IF($V31="","",IFERROR(INDEX(Articulacion!O:O,$V31),0))} | S31: {=IF($V31="","",IFERROR(INDEX(Articulacion!P:P,$V31),0))} | T31: {=IF($V31="","",IFERROR(INDEX(Articulacion!Q:Q,$V31),0))} | U31: =IF($V31="",0,SUM(J31:T31)) -> 0 | AN31: 2 | AO31: 1 | AP31: 1 | AQ31: 1 | AX31: =SUM(W31:AW31) -> 5 | AY31: =G31-U31-AX31 -> 0
A32: 64 | B32: 249124 | C32: Cosedora manual, de estructura íntegramente metálica (acero o aleaciones resistentes) papel de hasta 30 hojas, de grapas estándar 26/6 | D32: NA | E32: NA | F32: NA | G32: 17 | H32: 31092.44 | I32: 0 | J32: {=IF($V32="","",IFERROR(INDEX(Articulacion!G:G,$V32),0))} -> 1 | K32: {=IF($V32="","",IFERROR(INDEX(Articulacion!H:H,$V32),0))} -> 0 | L32: {=IF($V32="","",IFERROR(INDEX(Articulacion!I:I,$V32),0))} -> 0 | M32: {=IF($V32="","",IFERROR(INDEX(Articulacion!J:J,$V32),0))} -> 0 | N32: {=IF($V32="","",IFERROR(INDEX(Articulacion!K:K,$V32),0))} -> 0 | O32: {=IF($V32="","",IFERROR(INDEX(Articulacion!L:L,$V32),0))} -> 0 | P32: {=IF($V32="","",IFERROR(INDEX(Articulacion!M:M,$V32),0))} -> 1 | Q32: {=IF($V32="","",IFERROR(INDEX(Articulacion!N:N,$V32),0))} -> 0 | R32: {=IF($V32="","",IFERROR(INDEX(Articulacion!O:O,$V32),0))} -> 0 | S32: {=IF($V32="","",IFERROR(INDEX(Articulacion!P:P,$V32),0))} -> 0 | T32: {=IF($V32="","",IFERROR(INDEX(Articulacion!Q:Q,$V32),0))} -> 0 | U32: =IF($V32="",0,SUM(J32:T32)) -> 2 | V32: 5 | AJ32: 1 | AK32: 1 | AL32: 1 | AM32: 1 | AN32: 2 | AO32: 1 | AP32: 1 | AQ32: 1 | AR32: 1 | AS32: 1 | AT32: 1 | AU32: 1 | AV32: 1 | AW32: 1 | AX32: =SUM(W32:AW32) -> 15 | AY32: =G32-U32-AX32 -> 0
A33: 20 | B33: 280058 | C33: Crayolas extra gruesa paquete por 18 unidades, Colores: varios, Forma: cilíndrica | D33: NA | E33: NA | F33: NA | G33: 7 | H33: 50420.17 | I33: 0 | J33: {=IF($V33="","",IFERROR(INDEX(Articulacion!G:G,$V33),0))} | K33: {=IF($V33="","",IFERROR(INDEX(Articulacion!H:H,$V33),0))} | L33: {=IF($V33="","",IFERROR(INDEX(Articulacion!I:I,$V33),0))} | M33: {=IF($V33="","",IFERROR(INDEX(Articulacion!J:J,$V33),0))} | N33: {=IF($V33="","",IFERROR(INDEX(Articulacion!K:K,$V33),0))} | O33: {=IF($V33="","",IFERROR(INDEX(Articulacion!L:L,$V33),0))} | P33: {=IF($V33="","",IFERROR(INDEX(Articulacion!M:M,$V33),0))} | Q33: {=IF($V33="","",IFERROR(INDEX(Articulacion!N:N,$V33),0))} | R33: {=IF($V33="","",IFERROR(INDEX(Articulacion!O:O,$V33),0))} | S33: {=IF($V33="","",IFERROR(INDEX(Articulacion!P:P,$V33),0))} | T33: {=IF($V33="","",IFERROR(INDEX(Articulacion!Q:Q,$V33),0))} | U33: =IF($V33="",0,SUM(J33:T33)) -> 0 | AQ33: 4 | AR33: 3 | AX33: =SUM(W33:AW33) -> 7 | AY33: =G33-U33-AX33 -> 0
A34: 63 | B34: 290283 | C34: Escarcha líquida colores surtidos frasco 60 ml | D34: NA | E34: NA | F34: NA | G34: 8 | H34: 4621.85 | I34: 0 | J34: {=IF($V34="","",IFERROR(INDEX(Articulacion!G:G,$V34),0))} | K34: {=IF($V34="","",IFERROR(INDEX(Articulacion!H:H,$V34),0))} | L34: {=IF($V34="","",IFERROR(INDEX(Articulacion!I:I,$V34),0))} | M34: {=IF($V34="","",IFERROR(INDEX(Articulacion!J:J,$V34),0))} | N34: {=IF($V34="","",IFERROR(INDEX(Articulacion!K:K,$V34),0))} | O34: {=IF($V34="","",IFERROR(INDEX(Articulacion!L:L,$V34),0))} | P34: {=IF($V34="","",IFERROR(INDEX(Articulacion!M:M,$V34),0))} | Q34: {=IF($V34="","",IFERROR(INDEX(Articulacion!N:N,$V34),0))} | R34: {=IF($V34="","",IFERROR(INDEX(Articulacion!O:O,$V34),0))} | S34: {=IF($V34="","",IFERROR(INDEX(Articulacion!P:P,$V34),0))} | T34: {=IF($V34="","",IFERROR(INDEX(Articulacion!Q:Q,$V34),0))} | U34: =IF($V34="",0,SUM(J34:T34)) -> 0 | AN34: 1 | AO34: 1 | AP34: 1 | AQ34: 1 | AR34: 1 | AS34: 1 | AT34: 1 | AU34: 1 | AX34: =SUM(W34:AW34) -> 8 | AY34: =G34-U34-AX34 -> 0
A35: 62 | B35: 252977 | C35: Folder Blanco Tamaño Carta De 1 1/2 Pulgadas, 3,7cms Ancho | D35: NA | E35: NA | F35: NA | G35: 10 | H35: 22689.08 | I35: 0 | J35: {=IF($V35="","",IFERROR(INDEX(Articulacion!G:G,$V35),0))} | K35: {=IF($V35="","",IFERROR(INDEX(Articulacion!H:H,$V35),0))} | L35: {=IF($V35="","",IFERROR(INDEX(Articulacion!I:I,$V35),0))} | M35: {=IF($V35="","",IFERROR(INDEX(Articulacion!J:J,$V35),0))} | N35: {=IF($V35="","",IFERROR(INDEX(Articulacion!K:K,$V35),0))} | O35: {=IF($V35="","",IFERROR(INDEX(Articulacion!L:L,$V35),0))} | P35: {=IF($V35="","",IFERROR(INDEX(Articulacion!M:M,$V35),0))} | Q35: {=IF($V35="","",IFERROR(INDEX(Articulacion!N:N,$V35),0))} | R35: {=IF($V35="","",IFERROR(INDEX(Articulacion!O:O,$V35),0))} | S35: {=IF($V35="","",IFERROR(INDEX(Articulacion!P:P,$V35),0))} | T35: {=IF($V35="","",IFERROR(INDEX(Articulacion!Q:Q,$V35),0))} | U35: =IF($V35="",0,SUM(J35:T35)) -> 0 | W35: 1 | X35: 1 | Y35: 1 | Z35: 1 | AA35: 1 | AB35: 1 | AC35: 1 | AD35: 1 | AE35: 1 | AF35: 1 | AX35: =SUM(W35:AW35) -> 10 | AY35: =G35-U35-AX35 -> 0
A36: 16 | B36: 292269 | C36: Folders plásticos Tamaño: Carta Espesor del material: Entre 0.18 mm y 0.25 mm, colores surtidos azul, rojo, verde, amarillo, naranja y/o transparente. Tipo sobre o tipo carpeta simple. Bordes termosellados para mayor durabilidad, apertura: Lateral o superior, según diseño del fabricante. Acabado: Superficie lisa o ligeramente texturizada para evitar rayones. Capacidad: Apto para contener entre 20 y 40 hojas de papel bond de 75 g/m². Presentación: Paquete por 6 unidades, empacado y sellado. | D36: NA | E36: NA | F36: NA | G36: 6 | H36: 12605.04 | I36: 0 | J36: {=IF($V36="","",IFERROR(INDEX(Articulacion!G:G,$V36),0))} | K36: {=IF($V36="","",IFERROR(INDEX(Articulacion!H:H,$V36),0))} | L36: {=IF($V36="","",IFERROR(INDEX(Articulacion!I:I,$V36),0))} | M36: {=IF($V36="","",IFERROR(INDEX(Articulacion!J:J,$V36),0))} | N36: {=IF($V36="","",IFERROR(INDEX(Articulacion!K:K,$V36),0))} | O36: {=IF($V36="","",IFERROR(INDEX(Articulacion!L:L,$V36),0))} | P36: {=IF($V36="","",IFERROR(INDEX(Articulacion!M:M,$V36),0))} | Q36: {=IF($V36="","",IFERROR(INDEX(Articulacion!N:N,$V36),0))} | R36: {=IF($V36="","",IFERROR(INDEX(Articulacion!O:O,$V36),0))} | S36: {=IF($V36="","",IFERROR(INDEX(Articulacion!P:P,$V36),0))} | T36: {=IF($V36="","",IFERROR(INDEX(Articulacion!Q:Q,$V36),0))} | U36: =IF($V36="",0,SUM(J36:T36)) -> 0 | AG36: 1 | AH36: 1 | AI36: 1 | AJ36: 1 | AK36: 1 | AL36: 1 | AX36: =SUM(W36:AW36) -> 6 | AY36: =G36-U36-AX36 -> 0
A37: 9 | B37: 292316 | C37: Formato contrato a término indefinido, paquete, x 12, Unidades | D37: NA | E37: NA | F37: NA | G37: 3 | H37: 37815.13 | I37: 0 | J37: {=IF($V37="","",IFERROR(INDEX(Articulacion!G:G,$V37),0))} -> 1 | K37: {=IF($V37="","",IFERROR(INDEX(Articulacion!H:H,$V37),0))} -> 1 | L37: {=IF($V37="","",IFERROR(INDEX(Articulacion!I:I,$V37),0))} -> 1 | M37: {=IF($V37="","",IFERROR(INDEX(Articulacion!J:J,$V37),0))} -> 0 | N37: {=IF($V37="","",IFERROR(INDEX(Articulacion!K:K,$V37),0))} -> 0 | O37: {=IF($V37="","",IFERROR(INDEX(Articulacion!L:L,$V37),0))} -> 0 | P37: {=IF($V37="","",IFERROR(INDEX(Articulacion!M:M,$V37),0))} -> 0 | Q37: {=IF($V37="","",IFERROR(INDEX(Articulacion!N:N,$V37),0))} -> 0 | R37: {=IF($V37="","",IFERROR(INDEX(Articulacion!O:O,$V37),0))} -> 0 | S37: {=IF($V37="","",IFERROR(INDEX(Articulacion!P:P,$V37),0))} -> 0 | T37: {=IF($V37="","",IFERROR(INDEX(Articulacion!Q:Q,$V37),0))} -> 0 | U37: =IF($V37="",0,SUM(J37:T37)) -> 3 | V37: 13 | AX37: =SUM(W37:AW37) -> 0 | AY37: =G37-U37-AX37 -> 0
A38: 8 | B38: 280456 | C38: Formato contrato civil, paquete, x 12, unds | D38: NA | E38: NA | F38: NA | G38: 2 | H38: 36974.79 | I38: 0 | J38: {=IF($V38="","",IFERROR(INDEX(Articulacion!G:G,$V38),0))} -> 1 | K38: {=IF($V38="","",IFERROR(INDEX(Articulacion!H:H,$V38),0))} -> 0 | L38: {=IF($V38="","",IFERROR(INDEX(Articulacion!I:I,$V38),0))} -> 1 | M38: {=IF($V38="","",IFERROR(INDEX(Articulacion!J:J,$V38),0))} -> 0 | N38: {=IF($V38="","",IFERROR(INDEX(Articulacion!K:K,$V38),0))} -> 0 | O38: {=IF($V38="","",IFERROR(INDEX(Articulacion!L:L,$V38),0))} -> 0 | P38: {=IF($V38="","",IFERROR(INDEX(Articulacion!M:M,$V38),0))} -> 0 | Q38: {=IF($V38="","",IFERROR(INDEX(Articulacion!N:N,$V38),0))} -> 0 | R38: {=IF($V38="","",IFERROR(INDEX(Articulacion!O:O,$V38),0))} -> 0 | S38: {=IF($V38="","",IFERROR(INDEX(Articulacion!P:P,$V38),0))} -> 0 | T38: {=IF($V38="","",IFERROR(INDEX(Articulacion!Q:Q,$V38),0))} -> 0 | U38: =IF($V38="",0,SUM(J38:T38)) -> 2 | V38: 14 | AX38: =SUM(W38:AW38) -> 0 | AY38: =G38-U38-AX38 -> 0
A39: 7 | B39: 280456 | C39: formato contrato de trabajo a término fijo, paquete, x 12, Unds | D39: NA | E39: NA | F39: NA | G39: 3 | H39: 35294.12 | I39: 0 | J39: {=IF($V39="","",IFERROR(INDEX(Articulacion!G:G,$V39),0))} -> 1 | K39: {=IF($V39="","",IFERROR(INDEX(Articulacion!H:H,$V39),0))} -> 1 | L39: {=IF($V39="","",IFERROR(INDEX(Articulacion!I:I,$V39),0))} -> 1 | M39: {=IF($V39="","",IFERROR(INDEX(Articulacion!J:J,$V39),0))} -> 0 | N39: {=IF($V39="","",IFERROR(INDEX(Articulacion!K:K,$V39),0))} -> 0 | O39: {=IF($V39="","",IFERROR(INDEX(Articulacion!L:L,$V39),0))} -> 0 | P39: {=IF($V39="","",IFERROR(INDEX(Articulacion!M:M,$V39),0))} -> 0 | Q39: {=IF($V39="","",IFERROR(INDEX(Articulacion!N:N,$V39),0))} -> 0 | R39: {=IF($V39="","",IFERROR(INDEX(Articulacion!O:O,$V39),0))} -> 0 | S39: {=IF($V39="","",IFERROR(INDEX(Articulacion!P:P,$V39),0))} -> 0 | T39: {=IF($V39="","",IFERROR(INDEX(Articulacion!Q:Q,$V39),0))} -> 0 | U39: =IF($V39="",0,SUM(J39:T39)) -> 3 | V39: 15 | AX39: =SUM(W39:AW39) -> 0 | AY39: =G39-U39-AX39 -> 0
A40: 6 | B40: 253827 | C40: Formato hoja de vida sencilla, paquete, x, 10 unidades | D40: NA | E40: NA | F40: NA | G40: 7 | H40: 10084.03 | I40: 0 | J40: {=IF($V40="","",IFERROR(INDEX(Articulacion!G:G,$V40),0))} -> 1 | K40: {=IF($V40="","",IFERROR(INDEX(Articulacion!H:H,$V40),0))} -> 1 | L40: {=IF($V40="","",IFERROR(INDEX(Articulacion!I:I,$V40),0))} -> 1 | M40: {=IF($V40="","",IFERROR(INDEX(Articulacion!J:J,$V40),0))} -> 0 | N40: {=IF($V40="","",IFERROR(INDEX(Articulacion!K:K,$V40),0))} -> 0 | O40: {=IF($V40="","",IFERROR(INDEX(Articulacion!L:L,$V40),0))} -> 0 | P40: {=IF($V40="","",IFERROR(INDEX(Articulacion!M:M,$V40),0))} -> 4 | Q40: {=IF($V40="","",IFERROR(INDEX(Articulacion!N:N,$V40),0))} -> 0 | R40: {=IF($V40="","",IFERROR(INDEX(Articulacion!O:O,$V40),0))} -> 0 | S40: {=IF($V40="","",IFERROR(INDEX(Articulacion!P:P,$V40),0))} -> 0 | T40: {=IF($V40="","",IFERROR(INDEX(Articulacion!Q:Q,$V40),0))} -> 0 | U40: =IF($V40="",0,SUM(J40:T40)) -> 7 | V40: 16 | AX40: =SUM(W40:AW40) -> 0 | AY40: =G40-U40-AX40 -> 0
A41: 10 | B41: 287188 | C41: Formato pagaré paquete x 80 unidades | D41: NA | E41: NA | F41: NA | G41: 1 | H41: 151260.5 | I41: 0 | J41: {=IF($V41="","",IFERROR(INDEX(Articulacion!G:G,$V41),0))} -> 0 | K41: {=IF($V41="","",IFERROR(INDEX(Articulacion!H:H,$V41),0))} -> 0 | L41: {=IF($V41="","",IFERROR(INDEX(Articulacion!I:I,$V41),0))} -> 0 | M41: {=IF($V41="","",IFERROR(INDEX(Articulacion!J:J,$V41),0))} -> 0 | N41: {=IF($V41="","",IFERROR(INDEX(Articulacion!K:K,$V41),0))} -> 1 | O41: {=IF($V41="","",IFERROR(INDEX(Articulacion!L:L,$V41),0))} -> 0 | P41: {=IF($V41="","",IFERROR(INDEX(Articulacion!M:M,$V41),0))} -> 0 | Q41: {=IF($V41="","",IFERROR(INDEX(Articulacion!N:N,$V41),0))} -> 0 | R41: {=IF($V41="","",IFERROR(INDEX(Articulacion!O:O,$V41),0))} -> 0 | S41: {=IF($V41="","",IFERROR(INDEX(Articulacion!P:P,$V41),0))} -> 0 | T41: {=IF($V41="","",IFERROR(INDEX(Articulacion!Q:Q,$V41),0))} -> 0 | U41: =IF($V41="",0,SUM(J41:T41)) -> 1 | V41: 12 | AX41: =SUM(W41:AW41) -> 0 | AY41: =G41-U41-AX41 -> 0
A42: 90 | B42: 244571 | C42: Gancho Clip metálico recubierto en plástico en diferentes colores estándar caja x 100 | D42: NA | E42: NA | F42: NA | G42: 22 | H42: 3781.51 | I42: 0 | J42: {=IF($V42="","",IFERROR(INDEX(Articulacion!G:G,$V42),0))} | K42: {=IF($V42="","",IFERROR(INDEX(Articulacion!H:H,$V42),0))} | L42: {=IF($V42="","",IFERROR(INDEX(Articulacion!I:I,$V42),0))} | M42: {=IF($V42="","",IFERROR(INDEX(Articulacion!J:J,$V42),0))} | N42: {=IF($V42="","",IFERROR(INDEX(Articulacion!K:K,$V42),0))} | O42: {=IF($V42="","",IFERROR(INDEX(Articulacion!L:L,$V42),0))} | P42: {=IF($V42="","",IFERROR(INDEX(Articulacion!M:M,$V42),0))} | Q42: {=IF($V42="","",IFERROR(INDEX(Articulacion!N:N,$V42),0))} | R42: {=IF($V42="","",IFERROR(INDEX(Articulacion!O:O,$V42),0))} | S42: {=IF($V42="","",IFERROR(INDEX(Articulacion!P:P,$V42),0))} | T42: {=IF($V42="","",IFERROR(INDEX(Articulacion!Q:Q,$V42),0))} | U42: =IF($V42="",0,SUM(J42:T42)) -> 0 | W42: 1 | X42: 1 | Y42: 1 | Z42: 1 | AA42: 1 | AB42: 1 | AC42: 1 | AD42: 1 | AE42: 1 | AF42: 1 | AG42: 1 | AH42: 1 | AI42: 1 | AJ42: 1 | AK42: 1 | AL42: 1 | AM42: 1 | AN42: 2 | AO42: 1 | AP42: 1 | AQ42: 1 | AX42: =SUM(W42:AW42) -> 22 | AY42: =G42-U42-AX42 -> 0
A43: 18 | B43: 290133 | C43: Globos r12 marca paquete por 12 unidades, Tamaño inflado aprox 30 cm. Globos redondos de látex, colores sólidos y vibrantes para decorar eventos. | D43: NA | E43: NA | F43: NA | G43: 5 | H43: 21008.4 | I43: 0 | J43: {=IF($V43="","",IFERROR(INDEX(Articulacion!G:G,$V43),0))} | K43: {=IF($V43="","",IFERROR(INDEX(Articulacion!H:H,$V43),0))} | L43: {=IF($V43="","",IFERROR(INDEX(Articulacion!I:I,$V43),0))} | M43: {=IF($V43="","",IFERROR(INDEX(Articulacion!J:J,$V43),0))} | N43: {=IF($V43="","",IFERROR(INDEX(Articulacion!K:K,$V43),0))} | O43: {=IF($V43="","",IFERROR(INDEX(Articulacion!L:L,$V43),0))} | P43: {=IF($V43="","",IFERROR(INDEX(Articulacion!M:M,$V43),0))} | Q43: {=IF($V43="","",IFERROR(INDEX(Articulacion!N:N,$V43),0))} | R43: {=IF($V43="","",IFERROR(INDEX(Articulacion!O:O,$V43),0))} | S43: {=IF($V43="","",IFERROR(INDEX(Articulacion!P:P,$V43),0))} | T43: {=IF($V43="","",IFERROR(INDEX(Articulacion!Q:Q,$V43),0))} | U43: =IF($V43="",0,SUM(J43:T43)) -> 0 | AQ43: 3 | AR43: 2 | AX43: =SUM(W43:AW43) -> 5 | AY43: =G43-U43-AX43 -> 0
A44: 61 | B44: 260812 | C44: Grapa estándar galvanizada caja X 5000 unidades | D44: NA | E44: NA | F44: NA | G44: 7 | H44: 5882.35 | I44: 0 | J44: {=IF($V44="","",IFERROR(INDEX(Articulacion!G:G,$V44),0))} | K44: {=IF($V44="","",IFERROR(INDEX(Articulacion!H:H,$V44),0))} | L44: {=IF($V44="","",IFERROR(INDEX(Articulacion!I:I,$V44),0))} | M44: {=IF($V44="","",IFERROR(INDEX(Articulacion!J:J,$V44),0))} | N44: {=IF($V44="","",IFERROR(INDEX(Articulacion!K:K,$V44),0))} | O44: {=IF($V44="","",IFERROR(INDEX(Articulacion!L:L,$V44),0))} | P44: {=IF($V44="","",IFERROR(INDEX(Articulacion!M:M,$V44),0))} | Q44: {=IF($V44="","",IFERROR(INDEX(Articulacion!N:N,$V44),0))} | R44: {=IF($V44="","",IFERROR(INDEX(Articulacion!O:O,$V44),0))} | S44: {=IF($V44="","",IFERROR(INDEX(Articulacion!P:P,$V44),0))} | T44: {=IF($V44="","",IFERROR(INDEX(Articulacion!Q:Q,$V44),0))} | U44: =IF($V44="",0,SUM(J44:T44)) -> 0 | AG44: 1 | AH44: 1 | AI44: 1 | AJ44: 1 | AK44: 1 | AL44: 1 | AM44: 1 | AX44: =SUM(W44:AW44) -> 7 | AY44: =G44-U44-AX44 -> 0
A45: 59 | B45: 292307 | C45: Inflador, eléctrico, 2 boquillas, para globos | D45: NA | E45: NA | F45: NA | G45: 1 | H45: 117647.06 | I45: 0 | J45: {=IF($V45="","",IFERROR(INDEX(Articulacion!G:G,$V45),0))} | K45: {=IF($V45="","",IFERROR(INDEX(Articulacion!H:H,$V45),0))} | L45: {=IF($V45="","",IFERROR(INDEX(Articulacion!I:I,$V45),0))} | M45: {=IF($V45="","",IFERROR(INDEX(Articulacion!J:J,$V45),0))} | N45: {=IF($V45="","",IFERROR(INDEX(Articulacion!K:K,$V45),0))} | O45: {=IF($V45="","",IFERROR(INDEX(Articulacion!L:L,$V45),0))} | P45: {=IF($V45="","",IFERROR(INDEX(Articulacion!M:M,$V45),0))} | Q45: {=IF($V45="","",IFERROR(INDEX(Articulacion!N:N,$V45),0))} | R45: {=IF($V45="","",IFERROR(INDEX(Articulacion!O:O,$V45),0))} | S45: {=IF($V45="","",IFERROR(INDEX(Articulacion!P:P,$V45),0))} | T45: {=IF($V45="","",IFERROR(INDEX(Articulacion!Q:Q,$V45),0))} | U45: =IF($V45="",0,SUM(J45:T45)) -> 0 | AQ45: 1 | AX45: =SUM(W45:AW45) -> 1 | AY45: =G45-U45-AX45 -> 0
A46: 4 | B46: 299809 | C46: Juego De Mesa Monopoly Clásico Características del producto Características principales Nombre del juego de mesa Monopoly Clásico Modelo alfanumérico G0009 Idioma Español Formato Físico Tipo de juego Estrategia Componentes del juego Incluye tablero 8 peones 28 tarjetas de Título de Propiedad Largo del juego 4,1 cm Ancho del juego 26,7 cm Altura del juego 26,7 cm | D46: NA | E46: NA | F46: NA | G46: 5 | H46: 142857.14 | I46: 0 | J46: {=IF($V46="","",IFERROR(INDEX(Articulacion!G:G,$V46),0))} | K46: {=IF($V46="","",IFERROR(INDEX(Articulacion!H:H,$V46),0))} | L46: {=IF($V46="","",IFERROR(INDEX(Articulacion!I:I,$V46),0))} | M46: {=IF($V46="","",IFERROR(INDEX(Articulacion!J:J,$V46),0))} | N46: {=IF($V46="","",IFERROR(INDEX(Articulacion!K:K,$V46),0))} | O46: {=IF($V46="","",IFERROR(INDEX(Articulacion!L:L,$V46),0))} | P46: {=IF($V46="","",IFERROR(INDEX(Articulacion!M:M,$V46),0))} | Q46: {=IF($V46="","",IFERROR(INDEX(Articulacion!N:N,$V46),0))} | R46: {=IF($V46="","",IFERROR(INDEX(Articulacion!O:O,$V46),0))} | S46: {=IF($V46="","",IFERROR(INDEX(Articulacion!P:P,$V46),0))} | T46: {=IF($V46="","",IFERROR(INDEX(Articulacion!Q:Q,$V46),0))} | U46: =IF($V46="",0,SUM(J46:T46)) -> 0 | Y46: 1 | Z46: 1 | AA46: 1 | AB46: 1 | AC46: 1 | AX46: =SUM(W46:AW46) -> 5 | AY46: =G46-U46-AX46 -> 0
A47: 2 | B47: 244279 | C47: Juego Didáctico Tío Rico aprender Sobre Dinero Características del producto Características principales Nombre del juego de mesa McPato: La Aventura del Capitalismo Edición Tio Rico Idioma Español características Formato de venta Unidad Formato Físico Tipo de juego Juego de mesa educativo de economía y finanzas Componentes del juego Dinero de juego, Fichas, Tablero, cartas de lotería y sorpresa, casas y castillos Cantidad mínima de jugadores – Cantidad máxima de jugadores 2 – 6 Es un juego de cartas SI | D47: NA | E47: NA | F47: NA | G47: 3 | H47: 126050.42 | I47: 0 | J47: {=IF($V47="","",IFERROR(INDEX(Articulacion!G:G,$V47),0))} | K47: {=IF($V47="","",IFERROR(INDEX(Articulacion!H:H,$V47),0))} | L47: {=IF($V47="","",IFERROR(INDEX(Articulacion!I:I,$V47),0))} | M47: {=IF($V47="","",IFERROR(INDEX(Articulacion!J:J,$V47),0))} | N47: {=IF($V47="","",IFERROR(INDEX(Articulacion!K:K,$V47),0))} | O47: {=IF($V47="","",IFERROR(INDEX(Articulacion!L:L,$V47),0))} | P47: {=IF($V47="","",IFERROR(INDEX(Articulacion!M:M,$V47),0))} | Q47: {=IF($V47="","",IFERROR(INDEX(Articulacion!N:N,$V47),0))} | R47: {=IF($V47="","",IFERROR(INDEX(Articulacion!O:O,$V47),0))} | S47: {=IF($V47="","",IFERROR(INDEX(Articulacion!P:P,$V47),0))} | T47: {=IF($V47="","",IFERROR(INDEX(Articulacion!Q:Q,$V47),0))} | U47: =IF($V47="",0,SUM(J47:T47)) -> 0 | AD47: 1 | AE47: 1 | AF47: 1 | AX47: =SUM(W47:AW47) -> 3 | AY47: =G47-U47-AX47 -> 0
A48: 29 | B48: 292275 | C48: kit de oficina que contiene: A. Clips metálicos Material: alambre metálico galvanizado o niquelado. Tamaño: nº 1 o 28 mm (estándar). Color: surtido. Presentación: bolsa o compartimento con mínimo 50 unidades. Características: resistencia a la deformación, no se oxidan fácilmente. B. Manecillas (ganchos mariposa / fasteners) Material: metal o plástico resistente. Tamaño: 8 cm o estándar para archivadores. Color: surtido. Presentación: mínimo 12 unidades. Características: flexibles, resistentes y compatibles con carpetas de dos perforaciones. C. Chinches (tachuelas) Material: cabeza plástica o metálica con punta de acero. Color: surtidos o metálicos. Presentación: mínimo 30 unidades. Características: punta resistente, no se doblan fácilmente. D. Cauchos elásticos, Material: caucho natural o sintético de alta elasticidad. Tamaño: mediano (aprox. 5 cm a 7 cm de diámetro). Color: surtido. Presentación: mínimo 50 unidades. Características: alta resistencia al estiramiento y durabilidad. | D48: NA | E48: NA | F48: NA | G48: 1 | H48: 109243.7 | I48: 0 | J48: {=IF($V48="","",IFERROR(INDEX(Articulacion!G:G,$V48),0))} | K48: {=IF($V48="","",IFERROR(INDEX(Articulacion!H:H,$V48),0))} | L48: {=IF($V48="","",IFERROR(INDEX(Articulacion!I:I,$V48),0))} | M48: {=IF($V48="","",IFERROR(INDEX(Articulacion!J:J,$V48),0))} | N48: {=IF($V48="","",IFERROR(INDEX(Articulacion!K:K,$V48),0))} | O48: {=IF($V48="","",IFERROR(INDEX(Articulacion!L:L,$V48),0))} | P48: {=IF($V48="","",IFERROR(INDEX(Articulacion!M:M,$V48),0))} | Q48: {=IF($V48="","",IFERROR(INDEX(Articulacion!N:N,$V48),0))} | R48: {=IF($V48="","",IFERROR(INDEX(Articulacion!O:O,$V48),0))} | S48: {=IF($V48="","",IFERROR(INDEX(Articulacion!P:P,$V48),0))} | T48: {=IF($V48="","",IFERROR(INDEX(Articulacion!Q:Q,$V48),0))} | U48: =IF($V48="",0,SUM(J48:T48)) -> 0 | AS48: 1 | AX48: =SUM(W48:AW48) -> 1 | AY48: =G48-U48-AX48 -> 0
A49: 15 | B49: 296648 | C49: Lana acrílica de 10 gramos - x 12 unidades surtidas, especial para tus manualidades. | D49: NA | E49: NA | F49: NA | G49: 5 | H49: 16806.72 | I49: 0 | J49: {=IF($V49="","",IFERROR(INDEX(Articulacion!G:G,$V49),0))} | K49: {=IF($V49="","",IFERROR(INDEX(Articulacion!H:H,$V49),0))} | L49: {=IF($V49="","",IFERROR(INDEX(Articulacion!I:I,$V49),0))} | M49: {=IF($V49="","",IFERROR(INDEX(Articulacion!J:J,$V49),0))} | N49: {=IF($V49="","",IFERROR(INDEX(Articulacion!K:K,$V49),0))} | O49: {=IF($V49="","",IFERROR(INDEX(Articulacion!L:L,$V49),0))} | P49: {=IF($V49="","",IFERROR(INDEX(Articulacion!M:M,$V49),0))} | Q49: {=IF($V49="","",IFERROR(INDEX(Articulacion!N:N,$V49),0))} | R49: {=IF($V49="","",IFERROR(INDEX(Articulacion!O:O,$V49),0))} | S49: {=IF($V49="","",IFERROR(INDEX(Articulacion!P:P,$V49),0))} | T49: {=IF($V49="","",IFERROR(INDEX(Articulacion!Q:Q,$V49),0))} | U49: =IF($V49="",0,SUM(J49:T49)) -> 0 | AQ49: 2 | AR49: 3 | AX49: =SUM(W49:AW49) -> 5 | AY49: =G49-U49-AX49 -> 0
A50: 3 | B50: 292235 | C50: Lapicero Retráctil, de alta calidad, Tinta negra, Cuerpo en acrílico denso, Presentación: Caja x 12 unidades | D50: NA | E50: NA | F50: NA | G50: 5 | H50: 12605.04 | I50: 0 | J50: {=IF($V50="","",IFERROR(INDEX(Articulacion!G:G,$V50),0))} -> 1 | K50: {=IF($V50="","",IFERROR(INDEX(Articulacion!H:H,$V50),0))} -> 1 | L50: {=IF($V50="","",IFERROR(INDEX(Articulacion!I:I,$V50),0))} -> 0 | M50: {=IF($V50="","",IFERROR(INDEX(Articulacion!J:J,$V50),0))} -> 1 | N50: {=IF($V50="","",IFERROR(INDEX(Articulacion!K:K,$V50),0))} -> 1 | O50: {=IF($V50="","",IFERROR(INDEX(Articulacion!L:L,$V50),0))} -> 0 | P50: {=IF($V50="","",IFERROR(INDEX(Articulacion!M:M,$V50),0))} -> 1 | Q50: {=IF($V50="","",IFERROR(INDEX(Articulacion!N:N,$V50),0))} -> 0 | R50: {=IF($V50="","",IFERROR(INDEX(Articulacion!O:O,$V50),0))} -> 0 | S50: {=IF($V50="","",IFERROR(INDEX(Articulacion!P:P,$V50),0))} -> 0 | T50: {=IF($V50="","",IFERROR(INDEX(Articulacion!Q:Q,$V50),0))} -> 0 | U50: =IF($V50="",0,SUM(J50:T50)) -> 5 | V50: 18 | AX50: =SUM(W50:AW50) -> 0 | AY50: =G50-U50-AX50 -> 0
A51: 65 | B51: 290321 | C51: LÁPICES DE COLORES. de madera 100% reforestada fácil tajado, núcleos suaves, pigmentos de alta calidad, alto contenido de cera para un trazo más suave y un mayor y mejor cubrimiento, alto contenido de pigmento, mina gruesa de mínimo 3mm. caja x 12 unidades | D51: NA | E51: NA | F51: NA | G51: 15 | H51: 19327.73 | I51: 0 | J51: {=IF($V51="","",IFERROR(INDEX(Articulacion!G:G,$V51),0))} | K51: {=IF($V51="","",IFERROR(INDEX(Articulacion!H:H,$V51),0))} | L51: {=IF($V51="","",IFERROR(INDEX(Articulacion!I:I,$V51),0))} | M51: {=IF($V51="","",IFERROR(INDEX(Articulacion!J:J,$V51),0))} | N51: {=IF($V51="","",IFERROR(INDEX(Articulacion!K:K,$V51),0))} | O51: {=IF($V51="","",IFERROR(INDEX(Articulacion!L:L,$V51),0))} | P51: {=IF($V51="","",IFERROR(INDEX(Articulacion!M:M,$V51),0))} | Q51: {=IF($V51="","",IFERROR(INDEX(Articulacion!N:N,$V51),0))} | R51: {=IF($V51="","",IFERROR(INDEX(Articulacion!O:O,$V51),0))} | S51: {=IF($V51="","",IFERROR(INDEX(Articulacion!P:P,$V51),0))} | T51: {=IF($V51="","",IFERROR(INDEX(Articulacion!Q:Q,$V51),0))} | U51: =IF($V51="",0,SUM(J51:T51)) -> 0 | AG51: 1 | AH51: 1 | AI51: 1 | AJ51: 1 | AK51: 1 | AL51: 1 | AM51: 1 | AN51: 2 | AO51: 1 | AP51: 1 | AQ51: 1 | AR51: 1 | AS51: 1 | AT51: 1 | AX51: =SUM(W51:AW51) -> 15 | AY51: =G51-U51-AX51 -> 0
A52: 58 | B52: 292232 | C52: Lápiz Negro, No. 2, forma hexagonal ergonómica que facilita el agarre y evita deslizamientos, mina (HB) de trazo oscuro, con borrador libre de látex. CAJA X 12 UND | D52: NA | E52: NA | F52: NA | G52: 20 | H52: 1260.5 | I52: 0 | J52: {=IF($V52="","",IFERROR(INDEX(Articulacion!G:G,$V52),0))} | K52: {=IF($V52="","",IFERROR(INDEX(Articulacion!H:H,$V52),0))} | L52: {=IF($V52="","",IFERROR(INDEX(Articulacion!I:I,$V52),0))} | M52: {=IF($V52="","",IFERROR(INDEX(Articulacion!J:J,$V52),0))} | N52: {=IF($V52="","",IFERROR(INDEX(Articulacion!K:K,$V52),0))} | O52: {=IF($V52="","",IFERROR(INDEX(Articulacion!L:L,$V52),0))} | P52: {=IF($V52="","",IFERROR(INDEX(Articulacion!M:M,$V52),0))} | Q52: {=IF($V52="","",IFERROR(INDEX(Articulacion!N:N,$V52),0))} | R52: {=IF($V52="","",IFERROR(INDEX(Articulacion!O:O,$V52),0))} | S52: {=IF($V52="","",IFERROR(INDEX(Articulacion!P:P,$V52),0))} | T52: {=IF($V52="","",IFERROR(INDEX(Articulacion!Q:Q,$V52),0))} | U52: =IF($V52="",0,SUM(J52:T52)) -> 0 | W52: 1 | X52: 1 | Y52: 1 | Z52: 1 | AA52: 1 | AB52: 1 | AC52: 1 | AD52: 1 | AE52: 1 | AF52: 1 | AG52: 1 | AH52: 1 | AI52: 1 | AJ52: 1 | AK52: 1 | AL52: 1 | AM52: 1 | AN52: 2 | AO52: 1 | AX52: =SUM(W52:AW52) -> 20 | AY52: =G52-U52-AX52 -> 0
A53: 5 | B53: 292317 | C53: Libreta facturas Libro, de facturas, 1/2, carta | D53: NA | E53: NA | F53: NA | G53: 4 | H53: 10924.37 | I53: 0 | J53: {=IF($V53="","",IFERROR(INDEX(Articulacion!G:G,$V53),0))} -> 0 | K53: {=IF($V53="","",IFERROR(INDEX(Articulacion!H:H,$V53),0))} -> 0 | L53: {=IF($V53="","",IFERROR(INDEX(Articulacion!I:I,$V53),0))} -> 0 | M53: {=IF($V53="","",IFERROR(INDEX(Articulacion!J:J,$V53),0))} -> 2 | N53: {=IF($V53="","",IFERROR(INDEX(Articulacion!K:K,$V53),0))} -> 1 | O53: {=IF($V53="","",IFERROR(INDEX(Articulacion!L:L,$V53),0))} -> 1 | P53: {=IF($V53="","",IFERROR(INDEX(Articulacion!M:M,$V53),0))} -> 0 | Q53: {=IF($V53="","",IFERROR(INDEX(Articulacion!N:N,$V53),0))} -> 0 | R53: {=IF($V53="","",IFERROR(INDEX(Articulacion!O:O,$V53),0))} -> 0 | S53: {=IF($V53="","",IFERROR(INDEX(Articulacion!P:P,$V53),0))} -> 0 | T53: {=IF($V53="","",IFERROR(INDEX(Articulacion!Q:Q,$V53),0))} -> 0 | U53: =IF($V53="",0,SUM(J53:T53)) -> 4 | V53: 17 | AX53: =SUM(W53:AW53) -> 0 | AY53: =G53-U53-AX53 -> 0
A54: 14 | B54: 275126 | C54: Lienzos Infantiles Para Pintar Al Óleo, Marco Grande, 2 Unid | D54: NA | E54: NA | F54: NA | G54: 12 | H54: 37815.13 | I54: 0 | J54: {=IF($V54="","",IFERROR(INDEX(Articulacion!G:G,$V54),0))} | K54: {=IF($V54="","",IFERROR(INDEX(Articulacion!H:H,$V54),0))} | L54: {=IF($V54="","",IFERROR(INDEX(Articulacion!I:I,$V54),0))} | M54: {=IF($V54="","",IFERROR(INDEX(Articulacion!J:J,$V54),0))} | N54: {=IF($V54="","",IFERROR(INDEX(Articulacion!K:K,$V54),0))} | O54: {=IF($V54="","",IFERROR(INDEX(Articulacion!L:L,$V54),0))} | P54: {=IF($V54="","",IFERROR(INDEX(Articulacion!M:M,$V54),0))} | Q54: {=IF($V54="","",IFERROR(INDEX(Articulacion!N:N,$V54),0))} | R54: {=IF($V54="","",IFERROR(INDEX(Articulacion!O:O,$V54),0))} | S54: {=IF($V54="","",IFERROR(INDEX(Articulacion!P:P,$V54),0))} | T54: {=IF($V54="","",IFERROR(INDEX(Articulacion!Q:Q,$V54),0))} | U54: =IF($V54="",0,SUM(J54:T54)) -> 0 | AQ54: 6 | AR54: 6 | AX54: =SUM(W54:AW54) -> 12 | AY54: =G54-U54-AX54 -> 0
A55: 53 | B55: 240832 | C55: Marcador borrable colores Surtidos, Caja X 12 unidades. Marcador borrable colores Surtidos Para tableros acrílicos blancos borrables Punta resistente cuadrada | D55: NA | E55: NA | F55: NA | G55: 8 | H55: 33613.45 | I55: 0 | J55: {=IF($V55="","",IFERROR(INDEX(Articulacion!G:G,$V55),0))} | K55: {=IF($V55="","",IFERROR(INDEX(Articulacion!H:H,$V55),0))} | L55: {=IF($V55="","",IFERROR(INDEX(Articulacion!I:I,$V55),0))} | M55: {=IF($V55="","",IFERROR(INDEX(Articulacion!J:J,$V55),0))} | N55: {=IF($V55="","",IFERROR(INDEX(Articulacion!K:K,$V55),0))} | O55: {=IF($V55="","",IFERROR(INDEX(Articulacion!L:L,$V55),0))} | P55: {=IF($V55="","",IFERROR(INDEX(Articulacion!M:M,$V55),0))} | Q55: {=IF($V55="","",IFERROR(INDEX(Articulacion!N:N,$V55),0))} | R55: {=IF($V55="","",IFERROR(INDEX(Articulacion!O:O,$V55),0))} | S55: {=IF($V55="","",IFERROR(INDEX(Articulacion!P:P,$V55),0))} | T55: {=IF($V55="","",IFERROR(INDEX(Articulacion!Q:Q,$V55),0))} | U55: =IF($V55="",0,SUM(J55:T55)) -> 0 | W55: 1 | X55: 1 | Y55: 1 | Z55: 1 | AA55: 1 | AB55: 1 | AC55: 1 | AD55: 1 | AX55: =SUM(W55:AW55) -> 8 | AY55: =G55-U55-AX55 -> 0
A56: 52 | B56: 292225 | C56: Marcador Borrable de cuerpo redondo, Punta biselada de 3 anchos de línea, Tinta negra Para tablero blanco o vidrio, Presentación: Caja x 10 unidades | D56: NA | E56: NA | F56: NA | G56: 10 | H56: 29411.76 | I56: 0 | J56: {=IF($V56="","",IFERROR(INDEX(Articulacion!G:G,$V56),0))} | K56: {=IF($V56="","",IFERROR(INDEX(Articulacion!H:H,$V56),0))} | L56: {=IF($V56="","",IFERROR(INDEX(Articulacion!I:I,$V56),0))} | M56: {=IF($V56="","",IFERROR(INDEX(Articulacion!J:J,$V56),0))} | N56: {=IF($V56="","",IFERROR(INDEX(Articulacion!K:K,$V56),0))} | O56: {=IF($V56="","",IFERROR(INDEX(Articulacion!L:L,$V56),0))} | P56: {=IF($V56="","",IFERROR(INDEX(Articulacion!M:M,$V56),0))} | Q56: {=IF($V56="","",IFERROR(INDEX(Articulacion!N:N,$V56),0))} | R56: {=IF($V56="","",IFERROR(INDEX(Articulacion!O:O,$V56),0))} | S56: {=IF($V56="","",IFERROR(INDEX(Articulacion!P:P,$V56),0))} | T56: {=IF($V56="","",IFERROR(INDEX(Articulacion!Q:Q,$V56),0))} | U56: =IF($V56="",0,SUM(J56:T56)) -> 0 | AE56: 1 | AF56: 1 | AG56: 1 | AH56: 1 | AI56: 1 | AJ56: 1 | AK56: 1 | AL56: 1 | AM56: 1 | AN56: 1 | AX56: =SUM(W56:AW56) -> 10 | AY56: =G56-U56-AX56 -> 0
A57: 54 | B57: 272107 | C57: Marcador Borrable Marcadores acrílicos a base de pintura acrílica. Caja x10 unidades. incluidos: Set de 4 colores surtidos negro, blanco, rojo, azul; Punta: Punta fina o media aprox (0.7 mm a 2 mm) | D57: NA | E57: NA | F57: NA | G57: 3 | H57: 29411.76 | I57: 0 | J57: {=IF($V57="","",IFERROR(INDEX(Articulacion!G:G,$V57),0))} | K57: {=IF($V57="","",IFERROR(INDEX(Articulacion!H:H,$V57),0))} | L57: {=IF($V57="","",IFERROR(INDEX(Articulacion!I:I,$V57),0))} | M57: {=IF($V57="","",IFERROR(INDEX(Articulacion!J:J,$V57),0))} | N57: {=IF($V57="","",IFERROR(INDEX(Articulacion!K:K,$V57),0))} | O57: {=IF($V57="","",IFERROR(INDEX(Articulacion!L:L,$V57),0))} | P57: {=IF($V57="","",IFERROR(INDEX(Articulacion!M:M,$V57),0))} | Q57: {=IF($V57="","",IFERROR(INDEX(Articulacion!N:N,$V57),0))} | R57: {=IF($V57="","",IFERROR(INDEX(Articulacion!O:O,$V57),0))} | S57: {=IF($V57="","",IFERROR(INDEX(Articulacion!P:P,$V57),0))} | T57: {=IF($V57="","",IFERROR(INDEX(Articulacion!Q:Q,$V57),0))} | U57: =IF($V57="",0,SUM(J57:T57)) -> 0 | AQ57: 1 | AR57: 2 | AX57: =SUM(W57:AW57) -> 3 | AY57: =G57-U57-AX57 -> 0
A58: 50 | B58: 290357 | C58: Marcador permanente Tinta negra, punta fina. Caja X 12 unidades. Cuerpo redondo, Punta fina, tinta color negro, Permanente | D58: NA | E58: NA | F58: NA | G58: 12 | H58: 29411.76 | I58: 0 | J58: {=IF($V58="","",IFERROR(INDEX(Articulacion!G:G,$V58),0))} -> 0 | K58: {=IF($V58="","",IFERROR(INDEX(Articulacion!H:H,$V58),0))} -> 1 | L58: {=IF($V58="","",IFERROR(INDEX(Articulacion!I:I,$V58),0))} -> 1 | M58: {=IF($V58="","",IFERROR(INDEX(Articulacion!J:J,$V58),0))} -> 0 | N58: {=IF($V58="","",IFERROR(INDEX(Articulacion!K:K,$V58),0))} -> 0 | O58: {=IF($V58="","",IFERROR(INDEX(Articulacion!L:L,$V58),0))} -> 0 | P58: {=IF($V58="","",IFERROR(INDEX(Articulacion!M:M,$V58),0))} -> 0 | Q58: {=IF($V58="","",IFERROR(INDEX(Articulacion!N:N,$V58),0))} -> 0 | R58: {=IF($V58="","",IFERROR(INDEX(Articulacion!O:O,$V58),0))} -> 0 | S58: {=IF($V58="","",IFERROR(INDEX(Articulacion!P:P,$V58),0))} -> 0 | T58: {=IF($V58="","",IFERROR(INDEX(Articulacion!Q:Q,$V58),0))} -> 0 | U58: =IF($V58="",0,SUM(J58:T58)) -> 2 | V58: 8 | W58: 1 | X58: 1 | Y58: 1 | Z58: 1 | AA58: 1 | AB58: 1 | AC58: 1 | AD58: 1 | AE58: 1 | AF58: 1 | AX58: =SUM(W58:AW58) -> 10 | AY58: =G58-U58-AX58 -> 0
A59: 55 | B59: 272109 | C59: Marcador Punta fina colores surtidos Caja x 14 unidades Marcadores permanentes. Marca en: papel, plástico, metal y en la mayoría de las superficies. Colores intensos. Tinta que seca rápidamente, resistente a la decoloración y agua. | D59: NA | E59: NA | F59: NA | G59: 5 | H59: 54621.85 | I59: 0 | J59: {=IF($V59="","",IFERROR(INDEX(Articulacion!G:G,$V59),0))} | K59: {=IF($V59="","",IFERROR(INDEX(Articulacion!H:H,$V59),0))} | L59: {=IF($V59="","",IFERROR(INDEX(Articulacion!I:I,$V59),0))} | M59: {=IF($V59="","",IFERROR(INDEX(Articulacion!J:J,$V59),0))} | N59: {=IF($V59="","",IFERROR(INDEX(Articulacion!K:K,$V59),0))} | O59: {=IF($V59="","",IFERROR(INDEX(Articulacion!L:L,$V59),0))} | P59: {=IF($V59="","",IFERROR(INDEX(Articulacion!M:M,$V59),0))} | Q59: {=IF($V59="","",IFERROR(INDEX(Articulacion!N:N,$V59),0))} | R59: {=IF($V59="","",IFERROR(INDEX(Articulacion!O:O,$V59),0))} | S59: {=IF($V59="","",IFERROR(INDEX(Articulacion!P:P,$V59),0))} | T59: {=IF($V59="","",IFERROR(INDEX(Articulacion!Q:Q,$V59),0))} | U59: =IF($V59="",0,SUM(J59:T59)) -> 0 | AO59: 1 | AP59: 1 | AQ59: 1 | AR59: 1 | AS59: 1 | AX59: =SUM(W59:AW59) -> 5 | AY59: =G59-U59-AX59 -> 0
A60: 56 | B60: 240834 | C60: Marcador Punta fina Negro Caja x 14 unidades Marcadores permanentes. Marca en: papel, plástico, metal y en la mayoría de las superficies. Colores intensos. Tinta que seca rápidamente, resistente a la decoloración y agua. | D60: NA | E60: NA | F60: NA | G60: 9 | H60: 54621.85 | I60: 0 | J60: {=IF($V60="","",IFERROR(INDEX(Articulacion!G:G,$V60),0))} -> 0 | K60: {=IF($V60="","",IFERROR(INDEX(Articulacion!H:H,$V60),0))} -> 0 | L60: {=IF($V60="","",IFERROR(INDEX(Articulacion!I:I,$V60),0))} -> 1 | M60: {=IF($V60="","",IFERROR(INDEX(Articulacion!J:J,$V60),0))} -> 0 | N60: {=IF($V60="","",IFERROR(INDEX(Articulacion!K:K,$V60),0))} -> 0 | O60: {=IF($V60="","",IFERROR(INDEX(Articulacion!L:L,$V60),0))} -> 0 | P60: {=IF($V60="","",IFERROR(INDEX(Articulacion!M:M,$V60),0))} -> 0 | Q60: {=IF($V60="","",IFERROR(INDEX(Articulacion!N:N,$V60),0))} -> 0 | R60: {=IF($V60="","",IFERROR(INDEX(Articulacion!O:O,$V60),0))} -> 0 | S60: {=IF($V60="","",IFERROR(INDEX(Articulacion!P:P,$V60),0))} -> 0 | T60: {=IF($V60="","",IFERROR(INDEX(Articulacion!Q:Q,$V60),0))} -> 0 | U60: =IF($V60="",0,SUM(J60:T60)) -> 1 | V60: 6 | AP60: 1 | AQ60: 1 | AR60: 1 | AS60: 1 | AT60: 1 | AU60: 1 | AV60: 1 | AW60: 1 | AX60: =SUM(W60:AW60) -> 8 | AY60: =G60-U60-AX60 -> 0
A61: 49 | B61: 240858 | C61: Marcador Resaltador. Colores surtidos, Tinta no tóxica de alta luminosidad y resistencia, Punta biselada, Presentación: Caja x 10 unidades | D61: NA | E61: NA | F61: NA | G61: 10 | H61: 28571.43 | I61: 0 | J61: {=IF($V61="","",IFERROR(INDEX(Articulacion!G:G,$V61),0))} | K61: {=IF($V61="","",IFERROR(INDEX(Articulacion!H:H,$V61),0))} | L61: {=IF($V61="","",IFERROR(INDEX(Articulacion!I:I,$V61),0))} | M61: {=IF($V61="","",IFERROR(INDEX(Articulacion!J:J,$V61),0))} | N61: {=IF($V61="","",IFERROR(INDEX(Articulacion!K:K,$V61),0))} | O61: {=IF($V61="","",IFERROR(INDEX(Articulacion!L:L,$V61),0))} | P61: {=IF($V61="","",IFERROR(INDEX(Articulacion!M:M,$V61),0))} | Q61: {=IF($V61="","",IFERROR(INDEX(Articulacion!N:N,$V61),0))} | R61: {=IF($V61="","",IFERROR(INDEX(Articulacion!O:O,$V61),0))} | S61: {=IF($V61="","",IFERROR(INDEX(Articulacion!P:P,$V61),0))} | T61: {=IF($V61="","",IFERROR(INDEX(Articulacion!Q:Q,$V61),0))} | U61: =IF($V61="",0,SUM(J61:T61)) -> 0 | AG61: 1 | AH61: 1 | AI61: 1 | AJ61: 1 | AK61: 1 | AL61: 1 | AM61: 1 | AN61: 2 | AO61: 1 | AX61: =SUM(W61:AW61) -> 10 | AY61: =G61-U61-AX61 -> 0
A62: 51 | B62: 256519 | C62: MARCADORES PERMANENTES, colores surtidos, caja x 10 unidades. para uso permanente de secado rápido casi sin olor y resistente al agua, Punta resistente redonda | D62: NA | E62: NA | F62: NA | G62: 13 | H62: 28571.43 | I62: 0 | J62: {=IF($V62="","",IFERROR(INDEX(Articulacion!G:G,$V62),0))} -> 1 | K62: {=IF($V62="","",IFERROR(INDEX(Articulacion!H:H,$V62),0))} -> 0 | L62: {=IF($V62="","",IFERROR(INDEX(Articulacion!I:I,$V62),0))} -> 0 | M62: {=IF($V62="","",IFERROR(INDEX(Articulacion!J:J,$V62),0))} -> 0 | N62: {=IF($V62="","",IFERROR(INDEX(Articulacion!K:K,$V62),0))} -> 0 | O62: {=IF($V62="","",IFERROR(INDEX(Articulacion!L:L,$V62),0))} -> 1 | P62: {=IF($V62="","",IFERROR(INDEX(Articulacion!M:M,$V62),0))} -> 1 | Q62: {=IF($V62="","",IFERROR(INDEX(Articulacion!N:N,$V62),0))} -> 0 | R62: {=IF($V62="","",IFERROR(INDEX(Articulacion!O:O,$V62),0))} -> 0 | S62: {=IF($V62="","",IFERROR(INDEX(Articulacion!P:P,$V62),0))} -> 0 | T62: {=IF($V62="","",IFERROR(INDEX(Articulacion!Q:Q,$V62),0))} -> 0 | U62: =IF($V62="",0,SUM(J62:T62)) -> 3 | V62: 7 | AN62: 1 | AO62: 1 | AP62: 1 | AQ62: 1 | AR62: 1 | AS62: 1 | AT62: 1 | AU62: 1 | AV62: 1 | AW62: 1 | AX62: =SUM(W62:AW62) -> 10 | AY62: =G62-U62-AX62 -> 0
A63: 57 | B63: 280058 | C63: Material didáctico para actividades contables, contiene la estructura estandarizada del Plan Único de Cuentas utilizado en Colombia para el registro contable. Incluye la codificación, descripción y dinámica de cada una de las cuentas del activo, pasivo, patrimonio, ingresos, gastos y cuentas de orden. | D63: NA | E63: NA | F63: NA | G63: 19 | H63: 50420.17 | I63: 0 | J63: {=IF($V63="","",IFERROR(INDEX(Articulacion!G:G,$V63),0))} | K63: {=IF($V63="","",IFERROR(INDEX(Articulacion!H:H,$V63),0))} | L63: {=IF($V63="","",IFERROR(INDEX(Articulacion!I:I,$V63),0))} | M63: {=IF($V63="","",IFERROR(INDEX(Articulacion!J:J,$V63),0))} | N63: {=IF($V63="","",IFERROR(INDEX(Articulacion!K:K,$V63),0))} | O63: {=IF($V63="","",IFERROR(INDEX(Articulacion!L:L,$V63),0))} | P63: {=IF($V63="","",IFERROR(INDEX(Articulacion!M:M,$V63),0))} | Q63: {=IF($V63="","",IFERROR(INDEX(Articulacion!N:N,$V63),0))} | R63: {=IF($V63="","",IFERROR(INDEX(Articulacion!O:O,$V63),0))} | S63: {=IF($V63="","",IFERROR(INDEX(Articulacion!P:P,$V63),0))} | T63: {=IF($V63="","",IFERROR(INDEX(Articulacion!Q:Q,$V63),0))} | U63: =IF($V63="",0,SUM(J63:T63)) -> 0 | AI63: 3 | AJ63: 3 | AK63: 3 | AL63: 3 | AM63: 3 | AN63: 4 | AX63: =SUM(W63:AW63) -> 19 | AY63: =G63-U63-AX63 -> 0
A64: 48 | B64: 240835 | C64: MICROPUNTA DE TINTA NEGRA, ancho de trazo: 0.5 mm. punta de fibra y tinta húmeda acuosa. Punta de trazo fino indeformable. Caja x 10 unidades | D64: NA | E64: NA | F64: NA | G64: 2 | H64: 20168.07 | I64: 0 | J64: {=IF($V64="","",IFERROR(INDEX(Articulacion!G:G,$V64),0))} | K64: {=IF($V64="","",IFERROR(INDEX(Articulacion!H:H,$V64),0))} | L64: {=IF($V64="","",IFERROR(INDEX(Articulacion!I:I,$V64),0))} | M64: {=IF($V64="","",IFERROR(INDEX(Articulacion!J:J,$V64),0))} | N64: {=IF($V64="","",IFERROR(INDEX(Articulacion!K:K,$V64),0))} | O64: {=IF($V64="","",IFERROR(INDEX(Articulacion!L:L,$V64),0))} | P64: {=IF($V64="","",IFERROR(INDEX(Articulacion!M:M,$V64),0))} | Q64: {=IF($V64="","",IFERROR(INDEX(Articulacion!N:N,$V64),0))} | R64: {=IF($V64="","",IFERROR(INDEX(Articulacion!O:O,$V64),0))} | S64: {=IF($V64="","",IFERROR(INDEX(Articulacion!P:P,$V64),0))} | T64: {=IF($V64="","",IFERROR(INDEX(Articulacion!Q:Q,$V64),0))} | U64: =IF($V64="",0,SUM(J64:T64)) -> 0 | W64: 1 | X64: 1 | AX64: =SUM(W64:AW64) -> 2 | AY64: =G64-U64-AX64 -> 0
A65: 94 | B65: 292178 | C65: Notas Adhesivas X 400 Hojas 76x76 mm | D65: NA | E65: NA | F65: NA | G65: 15 | H65: 11764.71 | I65: 0 | J65: {=IF($V65="","",IFERROR(INDEX(Articulacion!G:G,$V65),0))} | K65: {=IF($V65="","",IFERROR(INDEX(Articulacion!H:H,$V65),0))} | L65: {=IF($V65="","",IFERROR(INDEX(Articulacion!I:I,$V65),0))} | M65: {=IF($V65="","",IFERROR(INDEX(Articulacion!J:J,$V65),0))} | N65: {=IF($V65="","",IFERROR(INDEX(Articulacion!K:K,$V65),0))} | O65: {=IF($V65="","",IFERROR(INDEX(Articulacion!L:L,$V65),0))} | P65: {=IF($V65="","",IFERROR(INDEX(Articulacion!M:M,$V65),0))} | Q65: {=IF($V65="","",IFERROR(INDEX(Articulacion!N:N,$V65),0))} | R65: {=IF($V65="","",IFERROR(INDEX(Articulacion!O:O,$V65),0))} | S65: {=IF($V65="","",IFERROR(INDEX(Articulacion!P:P,$V65),0))} | T65: {=IF($V65="","",IFERROR(INDEX(Articulacion!Q:Q,$V65),0))} | U65: =IF($V65="",0,SUM(J65:T65)) -> 0 | W65: 1 | X65: 1 | Y65: 1 | Z65: 1 | AA65: 1 | AB65: 1 | AC65: 1 | AD65: 1 | AE65: 1 | AF65: 1 | AG65: 1 | AH65: 1 | AI65: 1 | AJ65: 1 | AK65: 1 | AX65: =SUM(W65:AW65) -> 15 | AY65: =G65-U65-AX65 -> 0
A66: 13 | B66: 290365 | C66: Papel adhesivo Papel fotográfico brillante autoadhesivo de alta resolución, resistente al agua. Colores vivos y durables. Terminación: Brillante fotográfico. - Formato: A4 (210mm x 297mm). como CARTA. - Compatibilidad: impresoras de tinta (inkjet). - Tipo de tinta: DYE fotográfica. - Presentación: 10 hojas por paquete. - Aplicaciones: Ideal para imprimir stickers con calidad fotográfica, candy bar, etiquetas de productos y packaging. | D66: NA | E66: NA | F66: NA | G66: 5 | H66: 18487.39 | I66: 0 | J66: {=IF($V66="","",IFERROR(INDEX(Articulacion!G:G,$V66),0))} | K66: {=IF($V66="","",IFERROR(INDEX(Articulacion!H:H,$V66),0))} | L66: {=IF($V66="","",IFERROR(INDEX(Articulacion!I:I,$V66),0))} | M66: {=IF($V66="","",IFERROR(INDEX(Articulacion!J:J,$V66),0))} | N66: {=IF($V66="","",IFERROR(INDEX(Articulacion!K:K,$V66),0))} | O66: {=IF($V66="","",IFERROR(INDEX(Articulacion!L:L,$V66),0))} | P66: {=IF($V66="","",IFERROR(INDEX(Articulacion!M:M,$V66),0))} | Q66: {=IF($V66="","",IFERROR(INDEX(Articulacion!N:N,$V66),0))} | R66: {=IF($V66="","",IFERROR(INDEX(Articulacion!O:O,$V66),0))} | S66: {=IF($V66="","",IFERROR(INDEX(Articulacion!P:P,$V66),0))} | T66: {=IF($V66="","",IFERROR(INDEX(Articulacion!Q:Q,$V66),0))} | U66: =IF($V66="",0,SUM(J66:T66)) -> 0 | AQ66: 3 | AR66: 2 | AX66: =SUM(W66:AW66) -> 5 | AY66: =G66-U66-AX66 -> 0
A67: 47 | B67: 254780 | C67: Papel Bond X 25 Pliegos De 100 X 70 Cm De 115 Gr | D67: NA | E67: NA | F67: NA | G67: 12 | H67: 11764.71 | I67: 0 | J67: {=IF($V67="","",IFERROR(INDEX(Articulacion!G:G,$V67),0))} | K67: {=IF($V67="","",IFERROR(INDEX(Articulacion!H:H,$V67),0))} | L67: {=IF($V67="","",IFERROR(INDEX(Articulacion!I:I,$V67),0))} | M67: {=IF($V67="","",IFERROR(INDEX(Articulacion!J:J,$V67),0))} | N67: {=IF($V67="","",IFERROR(INDEX(Articulacion!K:K,$V67),0))} | O67: {=IF($V67="","",IFERROR(INDEX(Articulacion!L:L,$V67),0))} | P67: {=IF($V67="","",IFERROR(INDEX(Articulacion!M:M,$V67),0))} | Q67: {=IF($V67="","",IFERROR(INDEX(Articulacion!N:N,$V67),0))} | R67: {=IF($V67="","",IFERROR(INDEX(Articulacion!O:O,$V67),0))} | S67: {=IF($V67="","",IFERROR(INDEX(Articulacion!P:P,$V67),0))} | T67: {=IF($V67="","",IFERROR(INDEX(Articulacion!Q:Q,$V67),0))} | U67: =IF($V67="",0,SUM(J67:T67)) -> 0 | Y67: 1 | Z67: 1 | AA67: 1 | AB67: 1 | AC67: 1 | AD67: 1 | AE67: 1 | AF67: 1 | AG67: 1 | AH67: 1 | AI67: 1 | AJ67: 1 | AX67: =SUM(W67:AW67) -> 12 | AY67: =G67-U67-AX67 -> 0
A68: 46 | B68: 249130 | C68: Papel fommi Paquete de Fomii 1/8 colores surtidos, PAQUETE X 10 UNIDADES. | D68: NA | E68: NA | F68: NA | G68: 10 | H68: 23529.41 | I68: 0 | J68: {=IF($V68="","",IFERROR(INDEX(Articulacion!G:G,$V68),0))} | K68: {=IF($V68="","",IFERROR(INDEX(Articulacion!H:H,$V68),0))} | L68: {=IF($V68="","",IFERROR(INDEX(Articulacion!I:I,$V68),0))} | M68: {=IF($V68="","",IFERROR(INDEX(Articulacion!J:J,$V68),0))} | N68: {=IF($V68="","",IFERROR(INDEX(Articulacion!K:K,$V68),0))} | O68: {=IF($V68="","",IFERROR(INDEX(Articulacion!L:L,$V68),0))} | P68: {=IF($V68="","",IFERROR(INDEX(Articulacion!M:M,$V68),0))} | Q68: {=IF($V68="","",IFERROR(INDEX(Articulacion!N:N,$V68),0))} | R68: {=IF($V68="","",IFERROR(INDEX(Articulacion!O:O,$V68),0))} | S68: {=IF($V68="","",IFERROR(INDEX(Articulacion!P:P,$V68),0))} | T68: {=IF($V68="","",IFERROR(INDEX(Articulacion!Q:Q,$V68),0))} | U68: =IF($V68="",0,SUM(J68:T68)) -> 0 | AK68: 1 | AL68: 1 | AM68: 1 | AN68: 2 | AO68: 1 | AP68: 1 | AQ68: 1 | AR68: 1 | AS68: 1 | AX68: =SUM(W68:AW68) -> 10 | AY68: =G68-U68-AX68 -> 0
A69: 45 | B69: 278239 | C69: Papel Tipo Kraft, presentación: Rollo x 300 m, Gramaje: 90 g., Ancho: 91 cm. | D69: NA | E69: NA | F69: NA | G69: 3 | H69: 201680.67 | I69: 0 | J69: {=IF($V69="","",IFERROR(INDEX(Articulacion!G:G,$V69),0))} | K69: {=IF($V69="","",IFERROR(INDEX(Articulacion!H:H,$V69),0))} | L69: {=IF($V69="","",IFERROR(INDEX(Articulacion!I:I,$V69),0))} | M69: {=IF($V69="","",IFERROR(INDEX(Articulacion!J:J,$V69),0))} | N69: {=IF($V69="","",IFERROR(INDEX(Articulacion!K:K,$V69),0))} | O69: {=IF($V69="","",IFERROR(INDEX(Articulacion!L:L,$V69),0))} | P69: {=IF($V69="","",IFERROR(INDEX(Articulacion!M:M,$V69),0))} | Q69: {=IF($V69="","",IFERROR(INDEX(Articulacion!N:N,$V69),0))} | R69: {=IF($V69="","",IFERROR(INDEX(Articulacion!O:O,$V69),0))} | S69: {=IF($V69="","",IFERROR(INDEX(Articulacion!P:P,$V69),0))} | T69: {=IF($V69="","",IFERROR(INDEX(Articulacion!Q:Q,$V69),0))} | U69: =IF($V69="",0,SUM(J69:T69)) -> 0 | AT69: 1 | AU69: 1 | AV69: 1 | AX69: =SUM(W69:AW69) -> 3 | AY69: =G69-U69-AX69 -> 0
A70: 44 | B70: 290436 | C70: Pegante líquido, Tipo: Colbón, Envase ergonómico, Volumen de la unidad 250 cc | D70: NA | E70: NA | F70: NA | G70: 25 | H70: 6722.69 | I70: 0 | J70: {=IF($V70="","",IFERROR(INDEX(Articulacion!G:G,$V70),0))} | K70: {=IF($V70="","",IFERROR(INDEX(Articulacion!H:H,$V70),0))} | L70: {=IF($V70="","",IFERROR(INDEX(Articulacion!I:I,$V70),0))} | M70: {=IF($V70="","",IFERROR(INDEX(Articulacion!J:J,$V70),0))} | N70: {=IF($V70="","",IFERROR(INDEX(Articulacion!K:K,$V70),0))} | O70: {=IF($V70="","",IFERROR(INDEX(Articulacion!L:L,$V70),0))} | P70: {=IF($V70="","",IFERROR(INDEX(Articulacion!M:M,$V70),0))} | Q70: {=IF($V70="","",IFERROR(INDEX(Articulacion!N:N,$V70),0))} | R70: {=IF($V70="","",IFERROR(INDEX(Articulacion!O:O,$V70),0))} | S70: {=IF($V70="","",IFERROR(INDEX(Articulacion!P:P,$V70),0))} | T70: {=IF($V70="","",IFERROR(INDEX(Articulacion!Q:Q,$V70),0))} | U70: =IF($V70="",0,SUM(J70:T70)) -> 0 | W70: 1 | X70: 1 | Y70: 1 | Z70: 1 | AA70: 1 | AB70: 1 | AC70: 1 | AD70: 1 | AE70: 1 | AF70: 1 | AG70: 1 | AH70: 1 | AI70: 1 | AJ70: 1 | AK70: 1 | AL70: 1 | AM70: 1 | AN70: 2 | AO70: 1 | AP70: 1 | AQ70: 1 | AR70: 1 | AS70: 1 | AT70: 1 | AX70: =SUM(W70:AW70) -> 25 | AY70: =G70-U70-AX70 -> 0
A71: 85 | B71: 292203 | C71: Perforadora semi industrial 40 hojas Capacidad de perforado: 40 hojas de 75 gramos Ancho entre huecos: 80 milímetros Cuenta con guía de papel Fabricada toda en metal 2 huecos | D71: NA | E71: NA | F71: NA | G71: 10 | H71: 68907.56 | I71: 0 | J71: {=IF($V71="","",IFERROR(INDEX(Articulacion!G:G,$V71),0))} | K71: {=IF($V71="","",IFERROR(INDEX(Articulacion!H:H,$V71),0))} | L71: {=IF($V71="","",IFERROR(INDEX(Articulacion!I:I,$V71),0))} | M71: {=IF($V71="","",IFERROR(INDEX(Articulacion!J:J,$V71),0))} | N71: {=IF($V71="","",IFERROR(INDEX(Articulacion!K:K,$V71),0))} | O71: {=IF($V71="","",IFERROR(INDEX(Articulacion!L:L,$V71),0))} | P71: {=IF($V71="","",IFERROR(INDEX(Articulacion!M:M,$V71),0))} | Q71: {=IF($V71="","",IFERROR(INDEX(Articulacion!N:N,$V71),0))} | R71: {=IF($V71="","",IFERROR(INDEX(Articulacion!O:O,$V71),0))} | S71: {=IF($V71="","",IFERROR(INDEX(Articulacion!P:P,$V71),0))} | T71: {=IF($V71="","",IFERROR(INDEX(Articulacion!Q:Q,$V71),0))} | U71: =IF($V71="",0,SUM(J71:T71)) -> 0 | W71: 1 | X71: 1 | Y71: 1 | Z71: 1 | AA71: 1 | AB71: 1 | AC71: 1 | AD71: 1 | AE71: 1 | AF71: 1 | AX71: =SUM(W71:AW71) -> 10 | AY71: =G71-U71-AX71 -> 0
A72: 31 | B72: 230923 | C72: Pilas AA Pilas, tipo aa 1.5 v, juego x2 unidades, alkaline, composición química de las pilas: dióxido de manganeso, zinc, hidróxido de potasio, grafito y óxido, de zinc con fecha de vencimiento no inferior a 5 años. | D72: NA | E72: NA | F72: NA | G72: 10 | H72: 5882.35 | I72: 0 | J72: {=IF($V72="","",IFERROR(INDEX(Articulacion!G:G,$V72),0))} | K72: {=IF($V72="","",IFERROR(INDEX(Articulacion!H:H,$V72),0))} | L72: {=IF($V72="","",IFERROR(INDEX(Articulacion!I:I,$V72),0))} | M72: {=IF($V72="","",IFERROR(INDEX(Articulacion!J:J,$V72),0))} | N72: {=IF($V72="","",IFERROR(INDEX(Articulacion!K:K,$V72),0))} | O72: {=IF($V72="","",IFERROR(INDEX(Articulacion!L:L,$V72),0))} | P72: {=IF($V72="","",IFERROR(INDEX(Articulacion!M:M,$V72),0))} | Q72: {=IF($V72="","",IFERROR(INDEX(Articulacion!N:N,$V72),0))} | R72: {=IF($V72="","",IFERROR(INDEX(Articulacion!O:O,$V72),0))} | S72: {=IF($V72="","",IFERROR(INDEX(Articulacion!P:P,$V72),0))} | T72: {=IF($V72="","",IFERROR(INDEX(Articulacion!Q:Q,$V72),0))} | U72: =IF($V72="",0,SUM(J72:T72)) -> 0 | AA72: 1 | AB72: 1 | AC72: 1 | AD72: 1 | AE72: 1 | AF72: 1 | AG72: 1 | AH72: 1 | AI72: 1 | AJ72: 1 | AX72: =SUM(W72:AW72) -> 10 | AY72: =G72-U72-AX72 -> 0
A73: 30 | B73: 230924 | C73: Pilas AAA Pilas, tipo aaa 1.5 v, juego x2 unidades, alkaline, composición química de las pilas: dióxido de manganeso, zinc, hidróxido de potasio, grafito y óxido, de zinc con fecha de vencimiento no inferior a 5 años. | D73: NA | E73: NA | F73: NA | G73: 10 | H73: 5882.35 | I73: 0 | J73: {=IF($V73="","",IFERROR(INDEX(Articulacion!G:G,$V73),0))} | K73: {=IF($V73="","",IFERROR(INDEX(Articulacion!H:H,$V73),0))} | L73: {=IF($V73="","",IFERROR(INDEX(Articulacion!I:I,$V73),0))} | M73: {=IF($V73="","",IFERROR(INDEX(Articulacion!J:J,$V73),0))} | N73: {=IF($V73="","",IFERROR(INDEX(Articulacion!K:K,$V73),0))} | O73: {=IF($V73="","",IFERROR(INDEX(Articulacion!L:L,$V73),0))} | P73: {=IF($V73="","",IFERROR(INDEX(Articulacion!M:M,$V73),0))} | Q73: {=IF($V73="","",IFERROR(INDEX(Articulacion!N:N,$V73),0))} | R73: {=IF($V73="","",IFERROR(INDEX(Articulacion!O:O,$V73),0))} | S73: {=IF($V73="","",IFERROR(INDEX(Articulacion!P:P,$V73),0))} | T73: {=IF($V73="","",IFERROR(INDEX(Articulacion!Q:Q,$V73),0))} | U73: =IF($V73="",0,SUM(J73:T73)) -> 0 | AK73: 1 | AL73: 1 | AM73: 1 | AN73: 2 | AO73: 1 | AP73: 1 | AQ73: 1 | AR73: 1 | AS73: 1 | AX73: =SUM(W73:AW73) -> 10 | AY73: =G73-U73-AX73 -> 0
A74: 86 | B74: 290438 | C74: Pincel plano pelo de marta No. 12 | D74: NA | E74: NA | F74: NA | G74: 12 | H74: 15126.05 | I74: 0 | J74: {=IF($V74="","",IFERROR(INDEX(Articulacion!G:G,$V74),0))} | K74: {=IF($V74="","",IFERROR(INDEX(Articulacion!H:H,$V74),0))} | L74: {=IF($V74="","",IFERROR(INDEX(Articulacion!I:I,$V74),0))} | M74: {=IF($V74="","",IFERROR(INDEX(Articulacion!J:J,$V74),0))} | N74: {=IF($V74="","",IFERROR(INDEX(Articulacion!K:K,$V74),0))} | O74: {=IF($V74="","",IFERROR(INDEX(Articulacion!L:L,$V74),0))} | P74: {=IF($V74="","",IFERROR(INDEX(Articulacion!M:M,$V74),0))} | Q74: {=IF($V74="","",IFERROR(INDEX(Articulacion!N:N,$V74),0))} | R74: {=IF($V74="","",IFERROR(INDEX(Articulacion!O:O,$V74),0))} | S74: {=IF($V74="","",IFERROR(INDEX(Articulacion!P:P,$V74),0))} | T74: {=IF($V74="","",IFERROR(INDEX(Articulacion!Q:Q,$V74),0))} | U74: =IF($V74="",0,SUM(J74:T74)) -> 0 | AM74: 1 | AN74: 2 | AO74: 1 | AP74: 1 | AQ74: 1 | AR74: 1 | AS74: 1 | AT74: 1 | AU74: 1 | AV74: 1 | AW74: 1 | AX74: =SUM(W74:AW74) -> 12 | AY74: =G74-U74-AX74 -> 0
A75: 43 | B75: 303414 | C75: Pinceles Set Pincel Sintético X 10 unidades Óleo Acrílico Acuarela Pintura | D75: NA | E75: NA | F75: NA | G75: 5 | H75: 25210.08 | I75: 0 | J75: {=IF($V75="","",IFERROR(INDEX(Articulacion!G:G,$V75),0))} | K75: {=IF($V75="","",IFERROR(INDEX(Articulacion!H:H,$V75),0))} | L75: {=IF($V75="","",IFERROR(INDEX(Articulacion!I:I,$V75),0))} | M75: {=IF($V75="","",IFERROR(INDEX(Articulacion!J:J,$V75),0))} | N75: {=IF($V75="","",IFERROR(INDEX(Articulacion!K:K,$V75),0))} | O75: {=IF($V75="","",IFERROR(INDEX(Articulacion!L:L,$V75),0))} | P75: {=IF($V75="","",IFERROR(INDEX(Articulacion!M:M,$V75),0))} | Q75: {=IF($V75="","",IFERROR(INDEX(Articulacion!N:N,$V75),0))} | R75: {=IF($V75="","",IFERROR(INDEX(Articulacion!O:O,$V75),0))} | S75: {=IF($V75="","",IFERROR(INDEX(Articulacion!P:P,$V75),0))} | T75: {=IF($V75="","",IFERROR(INDEX(Articulacion!Q:Q,$V75),0))} | U75: =IF($V75="",0,SUM(J75:T75)) -> 0 | AS75: 1 | AT75: 1 | AU75: 1 | AV75: 1 | AW75: 1 | AX75: =SUM(W75:AW75) -> 5 | AY75: =G75-U75-AX75 -> 0
A76: 42 | B76: 231825 | C76: Pistola de silicona De alta calidad. de punta fina, Para barra delgada de 9 mm, Potencia mínima: 15W. Utiliza barras de silicona de tamaño estándar de 0.45 x 4. Diseño ergonómico. | D76: NA | E76: NA | F76: NA | G76: 1 | H76: 42016.81 | I76: 0 | J76: {=IF($V76="","",IFERROR(INDEX(Articulacion!G:G,$V76),0))} | K76: {=IF($V76="","",IFERROR(INDEX(Articulacion!H:H,$V76),0))} | L76: {=IF($V76="","",IFERROR(INDEX(Articulacion!I:I,$V76),0))} | M76: {=IF($V76="","",IFERROR(INDEX(Articulacion!J:J,$V76),0))} | N76: {=IF($V76="","",IFERROR(INDEX(Articulacion!K:K,$V76),0))} | O76: {=IF($V76="","",IFERROR(INDEX(Articulacion!L:L,$V76),0))} | P76: {=IF($V76="","",IFERROR(INDEX(Articulacion!M:M,$V76),0))} | Q76: {=IF($V76="","",IFERROR(INDEX(Articulacion!N:N,$V76),0))} | R76: {=IF($V76="","",IFERROR(INDEX(Articulacion!O:O,$V76),0))} | S76: {=IF($V76="","",IFERROR(INDEX(Articulacion!P:P,$V76),0))} | T76: {=IF($V76="","",IFERROR(INDEX(Articulacion!Q:Q,$V76),0))} | U76: =IF($V76="",0,SUM(J76:T76)) -> 0 | Y76: 1 | AX76: =SUM(W76:AW76) -> 1 | AY76: =G76-U76-AX76 -> 0
A77: 17 | B77: 235942 | C77: Producto editable Papel silueta de 75 grs/mtr2; colores surtidos diferentes tonalidades. Paquetes x 10 octavos. | D77: NA | E77: NA | F77: NA | G77: 10 | H77: 2941.18 | I77: 0 | J77: {=IF($V77="","",IFERROR(INDEX(Articulacion!G:G,$V77),0))} | K77: {=IF($V77="","",IFERROR(INDEX(Articulacion!H:H,$V77),0))} | L77: {=IF($V77="","",IFERROR(INDEX(Articulacion!I:I,$V77),0))} | M77: {=IF($V77="","",IFERROR(INDEX(Articulacion!J:J,$V77),0))} | N77: {=IF($V77="","",IFERROR(INDEX(Articulacion!K:K,$V77),0))} | O77: {=IF($V77="","",IFERROR(INDEX(Articulacion!L:L,$V77),0))} | P77: {=IF($V77="","",IFERROR(INDEX(Articulacion!M:M,$V77),0))} | Q77: {=IF($V77="","",IFERROR(INDEX(Articulacion!N:N,$V77),0))} | R77: {=IF($V77="","",IFERROR(INDEX(Articulacion!O:O,$V77),0))} | S77: {=IF($V77="","",IFERROR(INDEX(Articulacion!P:P,$V77),0))} | T77: {=IF($V77="","",IFERROR(INDEX(Articulacion!Q:Q,$V77),0))} | U77: =IF($V77="",0,SUM(J77:T77)) -> 0 | W77: 1 | X77: 1 | Y77: 1 | Z77: 1 | AA77: 1 | AB77: 1 | AC77: 1 | AD77: 1 | AE77: 1 | AF77: 1 | AX77: =SUM(W77:AW77) -> 10 | AY77: =G77-U77-AX77 -> 0
A78: 67 | B78: 292273 | C78: Producto editableClip mariposa caja X 50 unidades | D78: NA | E78: NA | F78: NA | G78: 5 | H78: 5042.02 | I78: 0 | J78: {=IF($V78="","",IFERROR(INDEX(Articulacion!G:G,$V78),0))} | K78: {=IF($V78="","",IFERROR(INDEX(Articulacion!H:H,$V78),0))} | L78: {=IF($V78="","",IFERROR(INDEX(Articulacion!I:I,$V78),0))} | M78: {=IF($V78="","",IFERROR(INDEX(Articulacion!J:J,$V78),0))} | N78: {=IF($V78="","",IFERROR(INDEX(Articulacion!K:K,$V78),0))} | O78: {=IF($V78="","",IFERROR(INDEX(Articulacion!L:L,$V78),0))} | P78: {=IF($V78="","",IFERROR(INDEX(Articulacion!M:M,$V78),0))} | Q78: {=IF($V78="","",IFERROR(INDEX(Articulacion!N:N,$V78),0))} | R78: {=IF($V78="","",IFERROR(INDEX(Articulacion!O:O,$V78),0))} | S78: {=IF($V78="","",IFERROR(INDEX(Articulacion!P:P,$V78),0))} | T78: {=IF($V78="","",IFERROR(INDEX(Articulacion!Q:Q,$V78),0))} | U78: =IF($V78="",0,SUM(J78:T78)) -> 0 | W78: 1 | X78: 1 | Y78: 1 | Z78: 1 | AA78: 1 | AX78: =SUM(W78:AW78) -> 5 | AY78: =G78-U78-AX78 -> 0
A79: 41 | B79: 290514 | C79: Regla plástica 50cm | D79: NA | E79: NA | F79: NA | G79: 20 | H79: 7563.03 | I79: 0 | J79: {=IF($V79="","",IFERROR(INDEX(Articulacion!G:G,$V79),0))} | K79: {=IF($V79="","",IFERROR(INDEX(Articulacion!H:H,$V79),0))} | L79: {=IF($V79="","",IFERROR(INDEX(Articulacion!I:I,$V79),0))} | M79: {=IF($V79="","",IFERROR(INDEX(Articulacion!J:J,$V79),0))} | N79: {=IF($V79="","",IFERROR(INDEX(Articulacion!K:K,$V79),0))} | O79: {=IF($V79="","",IFERROR(INDEX(Articulacion!L:L,$V79),0))} | P79: {=IF($V79="","",IFERROR(INDEX(Articulacion!M:M,$V79),0))} | Q79: {=IF($V79="","",IFERROR(INDEX(Articulacion!N:N,$V79),0))} | R79: {=IF($V79="","",IFERROR(INDEX(Articulacion!O:O,$V79),0))} | S79: {=IF($V79="","",IFERROR(INDEX(Articulacion!P:P,$V79),0))} | T79: {=IF($V79="","",IFERROR(INDEX(Articulacion!Q:Q,$V79),0))} | U79: =IF($V79="",0,SUM(J79:T79)) -> 0 | W79: 1 | X79: 1 | Y79: 1 | Z79: 1 | AA79: 1 | AB79: 1 | AC79: 1 | AD79: 1 | AE79: 1 | AF79: 1 | AG79: 1 | AH79: 1 | AI79: 1 | AJ79: 1 | AK79: 1 | AL79: 1 | AM79: 1 | AN79: 2 | AO79: 1 | AX79: =SUM(W79:AW79) -> 20 | AY79: =G79-U79-AX79 -> 0
A80: 40 | B80: 230881 | C80: Resma de Papel bond tamaño carta de 500 hojas, Color blanco, 75 gr | D80: NA | E80: NA | F80: NA | G80: 13 | H80: 19327.73 | I80: 0 | J80: {=IF($V80="","",IFERROR(INDEX(Articulacion!G:G,$V80),0))} -> 1 | K80: {=IF($V80="","",IFERROR(INDEX(Articulacion!H:H,$V80),0))} -> 0 | L80: {=IF($V80="","",IFERROR(INDEX(Articulacion!I:I,$V80),0))} -> 0 | M80: {=IF($V80="","",IFERROR(INDEX(Articulacion!J:J,$V80),0))} -> 0 | N80: {=IF($V80="","",IFERROR(INDEX(Articulacion!K:K,$V80),0))} -> 1 | O80: {=IF($V80="","",IFERROR(INDEX(Articulacion!L:L,$V80),0))} -> 0 | P80: {=IF($V80="","",IFERROR(INDEX(Articulacion!M:M,$V80),0))} -> 1 | Q80: {=IF($V80="","",IFERROR(INDEX(Articulacion!N:N,$V80),0))} -> 0 | R80: {=IF($V80="","",IFERROR(INDEX(Articulacion!O:O,$V80),0))} -> 0 | S80: {=IF($V80="","",IFERROR(INDEX(Articulacion!P:P,$V80),0))} -> 0 | T80: {=IF($V80="","",IFERROR(INDEX(Articulacion!Q:Q,$V80),0))} -> 0 | U80: =IF($V80="",0,SUM(J80:T80)) -> 3 | V80: 9 | AN80: 1 | AO80: 1 | AP80: 1 | AQ80: 1 | AR80: 1 | AS80: 1 | AT80: 1 | AU80: 1 | AV80: 1 | AW80: 1 | AX80: =SUM(W80:AW80) -> 10 | AY80: =G80-U80-AX80 -> 0
A81: 39 | B81: 230882 | C81: Resma Papel bond, tamaño oficio, de 500 hojas, Color blanco, 75 g | D81: NA | E81: NA | F81: NA | G81: 7 | H81: 21008.4 | I81: 0 | J81: {=IF($V81="","",IFERROR(INDEX(Articulacion!G:G,$V81),0))} | K81: {=IF($V81="","",IFERROR(INDEX(Articulacion!H:H,$V81),0))} | L81: {=IF($V81="","",IFERROR(INDEX(Articulacion!I:I,$V81),0))} | M81: {=IF($V81="","",IFERROR(INDEX(Articulacion!J:J,$V81),0))} | N81: {=IF($V81="","",IFERROR(INDEX(Articulacion!K:K,$V81),0))} | O81: {=IF($V81="","",IFERROR(INDEX(Articulacion!L:L,$V81),0))} | P81: {=IF($V81="","",IFERROR(INDEX(Articulacion!M:M,$V81),0))} | Q81: {=IF($V81="","",IFERROR(INDEX(Articulacion!N:N,$V81),0))} | R81: {=IF($V81="","",IFERROR(INDEX(Articulacion!O:O,$V81),0))} | S81: {=IF($V81="","",IFERROR(INDEX(Articulacion!P:P,$V81),0))} | T81: {=IF($V81="","",IFERROR(INDEX(Articulacion!Q:Q,$V81),0))} | U81: =IF($V81="",0,SUM(J81:T81)) -> 0 | W81: 1 | X81: 1 | Y81: 1 | Z81: 1 | AA81: 1 | AB81: 1 | AC81: 1 | AX81: =SUM(W81:AW81) -> 7 | AY81: =G81-U81-AX81 -> 0
A82: 12 | B82: 233019 | C82: Rompecabezas Fauna Silvestre 1000 pz | D82: NA | E82: NA | F82: NA | G82: 4 | H82: 11764.71 | I82: 0 | J82: {=IF($V82="","",IFERROR(INDEX(Articulacion!G:G,$V82),0))} -> 0 | K82: {=IF($V82="","",IFERROR(INDEX(Articulacion!H:H,$V82),0))} -> 0 | L82: {=IF($V82="","",IFERROR(INDEX(Articulacion!I:I,$V82),0))} -> 0 | M82: {=IF($V82="","",IFERROR(INDEX(Articulacion!J:J,$V82),0))} -> 0 | N82: {=IF($V82="","",IFERROR(INDEX(Articulacion!K:K,$V82),0))} -> 0 | O82: {=IF($V82="","",IFERROR(INDEX(Articulacion!L:L,$V82),0))} -> 0 | P82: {=IF($V82="","",IFERROR(INDEX(Articulacion!M:M,$V82),0))} -> 0 | Q82: {=IF($V82="","",IFERROR(INDEX(Articulacion!N:N,$V82),0))} -> 1 | R82: {=IF($V82="","",IFERROR(INDEX(Articulacion!O:O,$V82),0))} -> 1 | S82: {=IF($V82="","",IFERROR(INDEX(Articulacion!P:P,$V82),0))} -> 1 | T82: {=IF($V82="","",IFERROR(INDEX(Articulacion!Q:Q,$V82),0))} -> 1 | U82: =IF($V82="",0,SUM(J82:T82)) -> 4 | V82: 10 | AX82: =SUM(W82:AW82) -> 0 | AY82: =G82-U82-AX82 -> 0
A83: 33 | B83: 278263 | C83: Rótulo Adhesivo Transferencia Térmica desde 51x25mm Blanco Diseño impreso: Ninguno. autoadhesivo. presentación rollo | D83: NA | E83: NA | F83: NA | G83: 2 | H83: 92436.97 | I83: 0 | J83: {=IF($V83="","",IFERROR(INDEX(Articulacion!G:G,$V83),0))} | K83: {=IF($V83="","",IFERROR(INDEX(Articulacion!H:H,$V83),0))} | L83: {=IF($V83="","",IFERROR(INDEX(Articulacion!I:I,$V83),0))} | M83: {=IF($V83="","",IFERROR(INDEX(Articulacion!J:J,$V83),0))} | N83: {=IF($V83="","",IFERROR(INDEX(Articulacion!K:K,$V83),0))} | O83: {=IF($V83="","",IFERROR(INDEX(Articulacion!L:L,$V83),0))} | P83: {=IF($V83="","",IFERROR(INDEX(Articulacion!M:M,$V83),0))} | Q83: {=IF($V83="","",IFERROR(INDEX(Articulacion!N:N,$V83),0))} | R83: {=IF($V83="","",IFERROR(INDEX(Articulacion!O:O,$V83),0))} | S83: {=IF($V83="","",IFERROR(INDEX(Articulacion!P:P,$V83),0))} | T83: {=IF($V83="","",IFERROR(INDEX(Articulacion!Q:Q,$V83),0))} | U83: =IF($V83="",0,SUM(J83:T83)) -> 0 | W83: 1 | X83: 1 | AX83: =SUM(W83:AW83) -> 2 | AY83: =G83-U83-AX83 -> 0
A84: 24 | B84: 278263 | C84: Rótulos multiusos, características adhesivo resistente, de color amarillo con diámetro: 13 mm en paquete por 1134 unidades | D84: NA | E84: NA | F84: NA | G84: 3 | H84: 11764.71 | I84: 0 | J84: {=IF($V84="","",IFERROR(INDEX(Articulacion!G:G,$V84),0))} | K84: {=IF($V84="","",IFERROR(INDEX(Articulacion!H:H,$V84),0))} | L84: {=IF($V84="","",IFERROR(INDEX(Articulacion!I:I,$V84),0))} | M84: {=IF($V84="","",IFERROR(INDEX(Articulacion!J:J,$V84),0))} | N84: {=IF($V84="","",IFERROR(INDEX(Articulacion!K:K,$V84),0))} | O84: {=IF($V84="","",IFERROR(INDEX(Articulacion!L:L,$V84),0))} | P84: {=IF($V84="","",IFERROR(INDEX(Articulacion!M:M,$V84),0))} | Q84: {=IF($V84="","",IFERROR(INDEX(Articulacion!N:N,$V84),0))} | R84: {=IF($V84="","",IFERROR(INDEX(Articulacion!O:O,$V84),0))} | S84: {=IF($V84="","",IFERROR(INDEX(Articulacion!P:P,$V84),0))} | T84: {=IF($V84="","",IFERROR(INDEX(Articulacion!Q:Q,$V84),0))} | U84: =IF($V84="",0,SUM(J84:T84)) -> 0 | AQ84: 1 | AR84: 2 | AX84: =SUM(W84:AW84) -> 3 | AY84: =G84-U84-AX84 -> 0
A85: 25 | B85: 246712 | C85: Rótulos multiusos, características adhesivo resistente, de color rojo con diámetro: 13 mm en paquete por 1134 unidades | D85: NA | E85: NA | F85: NA | G85: 3 | H85: 11764.71 | I85: 0 | J85: {=IF($V85="","",IFERROR(INDEX(Articulacion!G:G,$V85),0))} | K85: {=IF($V85="","",IFERROR(INDEX(Articulacion!H:H,$V85),0))} | L85: {=IF($V85="","",IFERROR(INDEX(Articulacion!I:I,$V85),0))} | M85: {=IF($V85="","",IFERROR(INDEX(Articulacion!J:J,$V85),0))} | N85: {=IF($V85="","",IFERROR(INDEX(Articulacion!K:K,$V85),0))} | O85: {=IF($V85="","",IFERROR(INDEX(Articulacion!L:L,$V85),0))} | P85: {=IF($V85="","",IFERROR(INDEX(Articulacion!M:M,$V85),0))} | Q85: {=IF($V85="","",IFERROR(INDEX(Articulacion!N:N,$V85),0))} | R85: {=IF($V85="","",IFERROR(INDEX(Articulacion!O:O,$V85),0))} | S85: {=IF($V85="","",IFERROR(INDEX(Articulacion!P:P,$V85),0))} | T85: {=IF($V85="","",IFERROR(INDEX(Articulacion!Q:Q,$V85),0))} | U85: =IF($V85="",0,SUM(J85:T85)) -> 0 | AQ85: 2 | AR85: 1 | AX85: =SUM(W85:AW85) -> 3 | AY85: =G85-U85-AX85 -> 0
A86: 23 | B86: 278263 | C86: Rótulos multiusos, características adhesivo resistente, de color verde con diámetro: 13 mm en paquete por 1134 unidades | D86: NA | E86: NA | F86: NA | G86: 3 | H86: 11764.71 | I86: 0 | J86: {=IF($V86="","",IFERROR(INDEX(Articulacion!G:G,$V86),0))} | K86: {=IF($V86="","",IFERROR(INDEX(Articulacion!H:H,$V86),0))} | L86: {=IF($V86="","",IFERROR(INDEX(Articulacion!I:I,$V86),0))} | M86: {=IF($V86="","",IFERROR(INDEX(Articulacion!J:J,$V86),0))} | N86: {=IF($V86="","",IFERROR(INDEX(Articulacion!K:K,$V86),0))} | O86: {=IF($V86="","",IFERROR(INDEX(Articulacion!L:L,$V86),0))} | P86: {=IF($V86="","",IFERROR(INDEX(Articulacion!M:M,$V86),0))} | Q86: {=IF($V86="","",IFERROR(INDEX(Articulacion!N:N,$V86),0))} | R86: {=IF($V86="","",IFERROR(INDEX(Articulacion!O:O,$V86),0))} | S86: {=IF($V86="","",IFERROR(INDEX(Articulacion!P:P,$V86),0))} | T86: {=IF($V86="","",IFERROR(INDEX(Articulacion!Q:Q,$V86),0))} | U86: =IF($V86="",0,SUM(J86:T86)) -> 0 | AQ86: 2 | AR86: 1 | AX86: =SUM(W86:AW86) -> 3 | AY86: =G86-U86-AX86 -> 0
A87: 38 | B87: 292209 | C87: Saca gancho/grapas metálicas | D87: NA | E87: NA | F87: NA | G87: 25 | H87: 3361.34 | I87: 0 | J87: {=IF($V87="","",IFERROR(INDEX(Articulacion!G:G,$V87),0))} | K87: {=IF($V87="","",IFERROR(INDEX(Articulacion!H:H,$V87),0))} | L87: {=IF($V87="","",IFERROR(INDEX(Articulacion!I:I,$V87),0))} | M87: {=IF($V87="","",IFERROR(INDEX(Articulacion!J:J,$V87),0))} | N87: {=IF($V87="","",IFERROR(INDEX(Articulacion!K:K,$V87),0))} | O87: {=IF($V87="","",IFERROR(INDEX(Articulacion!L:L,$V87),0))} | P87: {=IF($V87="","",IFERROR(INDEX(Articulacion!M:M,$V87),0))} | Q87: {=IF($V87="","",IFERROR(INDEX(Articulacion!N:N,$V87),0))} | R87: {=IF($V87="","",IFERROR(INDEX(Articulacion!O:O,$V87),0))} | S87: {=IF($V87="","",IFERROR(INDEX(Articulacion!P:P,$V87),0))} | T87: {=IF($V87="","",IFERROR(INDEX(Articulacion!Q:Q,$V87),0))} | U87: =IF($V87="",0,SUM(J87:T87)) -> 0 | W87: 5 | X87: 5 | Y87: 1 | Z87: 1 | AA87: 1 | AB87: 1 | AC87: 1 | AD87: 1 | AE87: 1 | AF87: 1 | AG87: 1 | AH87: 1 | AI87: 1 | AJ87: 1 | AK87: 1 | AL87: 1 | AM87: 1 | AX87: =SUM(W87:AW87) -> 25 | AY87: =G87-U87-AX87 -> 0
A88: 37 | B88: 292221 | C88: Sacapuntas Presentación: caja x 24 unidades, Metálico, Material de hoja: Acero, Forma rectangular | D88: NA | E88: NA | F88: NA | G88: 5 | H88: 11764.71 | I88: 0 | J88: {=IF($V88="","",IFERROR(INDEX(Articulacion!G:G,$V88),0))} | K88: {=IF($V88="","",IFERROR(INDEX(Articulacion!H:H,$V88),0))} | L88: {=IF($V88="","",IFERROR(INDEX(Articulacion!I:I,$V88),0))} | M88: {=IF($V88="","",IFERROR(INDEX(Articulacion!J:J,$V88),0))} | N88: {=IF($V88="","",IFERROR(INDEX(Articulacion!K:K,$V88),0))} | O88: {=IF($V88="","",IFERROR(INDEX(Articulacion!L:L,$V88),0))} | P88: {=IF($V88="","",IFERROR(INDEX(Articulacion!M:M,$V88),0))} | Q88: {=IF($V88="","",IFERROR(INDEX(Articulacion!N:N,$V88),0))} | R88: {=IF($V88="","",IFERROR(INDEX(Articulacion!O:O,$V88),0))} | S88: {=IF($V88="","",IFERROR(INDEX(Articulacion!P:P,$V88),0))} | T88: {=IF($V88="","",IFERROR(INDEX(Articulacion!Q:Q,$V88),0))} | U88: =IF($V88="",0,SUM(J88:T88)) -> 0 | AN88: 2 | AO88: 1 | AP88: 1 | AQ88: 1 | AX88: =SUM(W88:AW88) -> 5 | AY88: =G88-U88-AX88 -> 0
A89: 89 | B89: 280058 | C89: Sello radiadores de correspondencia, recibida, despachada, fecha hora, entrante, saliente, Número de radicado | D89: NA | E89: NA | F89: NA | G89: 15 | H89: 71428.57 | I89: 0 | J89: {=IF($V89="","",IFERROR(INDEX(Articulacion!G:G,$V89),0))} | K89: {=IF($V89="","",IFERROR(INDEX(Articulacion!H:H,$V89),0))} | L89: {=IF($V89="","",IFERROR(INDEX(Articulacion!I:I,$V89),0))} | M89: {=IF($V89="","",IFERROR(INDEX(Articulacion!J:J,$V89),0))} | N89: {=IF($V89="","",IFERROR(INDEX(Articulacion!K:K,$V89),0))} | O89: {=IF($V89="","",IFERROR(INDEX(Articulacion!L:L,$V89),0))} | P89: {=IF($V89="","",IFERROR(INDEX(Articulacion!M:M,$V89),0))} | Q89: {=IF($V89="","",IFERROR(INDEX(Articulacion!N:N,$V89),0))} | R89: {=IF($V89="","",IFERROR(INDEX(Articulacion!O:O,$V89),0))} | S89: {=IF($V89="","",IFERROR(INDEX(Articulacion!P:P,$V89),0))} | T89: {=IF($V89="","",IFERROR(INDEX(Articulacion!Q:Q,$V89),0))} | U89: =IF($V89="",0,SUM(J89:T89)) -> 0 | W89: 7 | X89: 8 | AX89: =SUM(W89:AW89) -> 15 | AY89: =G89-U89-AX89 -> 0
A90: 28 | B90: 273571 | C90: Tabla A4 legajadora con tapa Tamaño: A4 (21 cm x 29.7 cm). Material: Cartón plastificado, PVC rígido, polipropileno (PP) o material similar de alta resistencia. Tapa frontal protectora tipo carpeta. Flexible o semirrígida, Cierre por broche, elástico o solapa. Resistente, anticorrosivo y de apertura fácil Color: Surtido o institucional (azul, negro, rojo, verde, etc.). Apta para archivar entre 150 y 250 hojas de papel bond de 75 g/m². Superficie lisa o texturizada. Presentación: Unidad empacada y Sellada | D90: NA | E90: NA | F90: NA | G90: 8 | H90: 33613.45 | I90: 0 | J90: {=IF($V90="","",IFERROR(INDEX(Articulacion!G:G,$V90),0))} | K90: {=IF($V90="","",IFERROR(INDEX(Articulacion!H:H,$V90),0))} | L90: {=IF($V90="","",IFERROR(INDEX(Articulacion!I:I,$V90),0))} | M90: {=IF($V90="","",IFERROR(INDEX(Articulacion!J:J,$V90),0))} | N90: {=IF($V90="","",IFERROR(INDEX(Articulacion!K:K,$V90),0))} | O90: {=IF($V90="","",IFERROR(INDEX(Articulacion!L:L,$V90),0))} | P90: {=IF($V90="","",IFERROR(INDEX(Articulacion!M:M,$V90),0))} | Q90: {=IF($V90="","",IFERROR(INDEX(Articulacion!N:N,$V90),0))} | R90: {=IF($V90="","",IFERROR(INDEX(Articulacion!O:O,$V90),0))} | S90: {=IF($V90="","",IFERROR(INDEX(Articulacion!P:P,$V90),0))} | T90: {=IF($V90="","",IFERROR(INDEX(Articulacion!Q:Q,$V90),0))} | U90: =IF($V90="",0,SUM(J90:T90)) -> 0 | W90: 1 | X90: 1 | Y90: 1 | Z90: 1 | AA90: 1 | AB90: 1 | AC90: 1 | AD90: 1 | AX90: =SUM(W90:AW90) -> 8 | AY90: =G90-U90-AX90 -> 0
A91: 36 | B91: 290151 | C91: Tabla legajadora Oficio, plástico, colores, surtidos con gancho | D91: NA | E91: NA | F91: NA | G91: 10 | H91: 10084.03 | I91: 0 | J91: {=IF($V91="","",IFERROR(INDEX(Articulacion!G:G,$V91),0))} | K91: {=IF($V91="","",IFERROR(INDEX(Articulacion!H:H,$V91),0))} | L91: {=IF($V91="","",IFERROR(INDEX(Articulacion!I:I,$V91),0))} | M91: {=IF($V91="","",IFERROR(INDEX(Articulacion!J:J,$V91),0))} | N91: {=IF($V91="","",IFERROR(INDEX(Articulacion!K:K,$V91),0))} | O91: {=IF($V91="","",IFERROR(INDEX(Articulacion!L:L,$V91),0))} | P91: {=IF($V91="","",IFERROR(INDEX(Articulacion!M:M,$V91),0))} | Q91: {=IF($V91="","",IFERROR(INDEX(Articulacion!N:N,$V91),0))} | R91: {=IF($V91="","",IFERROR(INDEX(Articulacion!O:O,$V91),0))} | S91: {=IF($V91="","",IFERROR(INDEX(Articulacion!P:P,$V91),0))} | T91: {=IF($V91="","",IFERROR(INDEX(Articulacion!Q:Q,$V91),0))} | U91: =IF($V91="",0,SUM(J91:T91)) -> 0 | W91: 1 | X91: 1 | Y91: 1 | Z91: 1 | AA91: 1 | AB91: 1 | AC91: 1 | AD91: 1 | AE91: 1 | AF91: 1 | AX91: =SUM(W91:AW91) -> 10 | AY91: =G91-U91-AX91 -> 0
A92: 21 | B92: 240861 | C92: Tajalápiz manual con depósito integrado para residuos, material del cuerpo plástico resistente (ABS o polipropileno), Cuchilla acero inoxidable de alta durabilidad, afilado corte uniforme, apto para lápices de grafito y color estándar, tamaño del orificio estándar para lápices de 7-8 mm de diámetro, depósito integrado, transparente u opaco, tapa o cierre seguro, colores surtidos. Presentación por unidad | D92: NA | E92: NA | F92: NA | G92: 10 | H92: 3781.51 | I92: 0 | J92: {=IF($V92="","",IFERROR(INDEX(Articulacion!G:G,$V92),0))} | K92: {=IF($V92="","",IFERROR(INDEX(Articulacion!H:H,$V92),0))} | L92: {=IF($V92="","",IFERROR(INDEX(Articulacion!I:I,$V92),0))} | M92: {=IF($V92="","",IFERROR(INDEX(Articulacion!J:J,$V92),0))} | N92: {=IF($V92="","",IFERROR(INDEX(Articulacion!K:K,$V92),0))} | O92: {=IF($V92="","",IFERROR(INDEX(Articulacion!L:L,$V92),0))} | P92: {=IF($V92="","",IFERROR(INDEX(Articulacion!M:M,$V92),0))} | Q92: {=IF($V92="","",IFERROR(INDEX(Articulacion!N:N,$V92),0))} | R92: {=IF($V92="","",IFERROR(INDEX(Articulacion!O:O,$V92),0))} | S92: {=IF($V92="","",IFERROR(INDEX(Articulacion!P:P,$V92),0))} | T92: {=IF($V92="","",IFERROR(INDEX(Articulacion!Q:Q,$V92),0))} | U92: =IF($V92="",0,SUM(J92:T92)) -> 0 | W92: 1 | X92: 1 | Y92: 1 | Z92: 1 | AA92: 1 | AB92: 1 | AC92: 1 | AD92: 1 | AE92: 1 | AF92: 1 | AX92: =SUM(W92:AW92) -> 10 | AY92: =G92-U92-AX92 -> 0
A93: 35 | B93: 292217 | C93: Tijeras oficina con cuchillas de acero inoxidable, 21 cm, Sencillo corte recto | D93: NA | E93: NA | F93: NA | G93: 10 | H93: 11764.71 | I93: 0 | J93: {=IF($V93="","",IFERROR(INDEX(Articulacion!G:G,$V93),0))} | K93: {=IF($V93="","",IFERROR(INDEX(Articulacion!H:H,$V93),0))} | L93: {=IF($V93="","",IFERROR(INDEX(Articulacion!I:I,$V93),0))} | M93: {=IF($V93="","",IFERROR(INDEX(Articulacion!J:J,$V93),0))} | N93: {=IF($V93="","",IFERROR(INDEX(Articulacion!K:K,$V93),0))} | O93: {=IF($V93="","",IFERROR(INDEX(Articulacion!L:L,$V93),0))} | P93: {=IF($V93="","",IFERROR(INDEX(Articulacion!M:M,$V93),0))} | Q93: {=IF($V93="","",IFERROR(INDEX(Articulacion!N:N,$V93),0))} | R93: {=IF($V93="","",IFERROR(INDEX(Articulacion!O:O,$V93),0))} | S93: {=IF($V93="","",IFERROR(INDEX(Articulacion!P:P,$V93),0))} | T93: {=IF($V93="","",IFERROR(INDEX(Articulacion!Q:Q,$V93),0))} | U93: =IF($V93="",0,SUM(J93:T93)) -> 0 | AG93: 1 | AH93: 1 | AI93: 1 | AJ93: 1 | AK93: 1 | AL93: 1 | AM93: 1 | AN93: 2 | AO93: 1 | AX93: =SUM(W93:AW93) -> 10 | AY93: =G93-U93-AX93 -> 0
A94: 34 | B94: 292218 | C94: Tijeras oficina Longitud desde 13 cm, material de las hojas: acero inoxidable de alta resistencia, filo recto, afilado, apto para cortes precisos, punta redondeada, material del mango plástico ABS o polipropileno resistente, mangos anatómicos para uso cómodo y prolongado. Presentación Unidad empacada y sellada | D94: NA | E94: NA | F94: NA | G94: 10 | H94: 10084.03 | I94: 0 | J94: {=IF($V94="","",IFERROR(INDEX(Articulacion!G:G,$V94),0))} | K94: {=IF($V94="","",IFERROR(INDEX(Articulacion!H:H,$V94),0))} | L94: {=IF($V94="","",IFERROR(INDEX(Articulacion!I:I,$V94),0))} | M94: {=IF($V94="","",IFERROR(INDEX(Articulacion!J:J,$V94),0))} | N94: {=IF($V94="","",IFERROR(INDEX(Articulacion!K:K,$V94),0))} | O94: {=IF($V94="","",IFERROR(INDEX(Articulacion!L:L,$V94),0))} | P94: {=IF($V94="","",IFERROR(INDEX(Articulacion!M:M,$V94),0))} | Q94: {=IF($V94="","",IFERROR(INDEX(Articulacion!N:N,$V94),0))} | R94: {=IF($V94="","",IFERROR(INDEX(Articulacion!O:O,$V94),0))} | S94: {=IF($V94="","",IFERROR(INDEX(Articulacion!P:P,$V94),0))} | T94: {=IF($V94="","",IFERROR(INDEX(Articulacion!Q:Q,$V94),0))} | U94: =IF($V94="",0,SUM(J94:T94)) -> 0 | AN94: 1 | AO94: 1 | AP94: 1 | AQ94: 1 | AR94: 1 | AS94: 1 | AT94: 1 | AU94: 1 | AV94: 1 | AW94: 1 | AX94: =SUM(W94:AW94) -> 10 | AY94: =G94-U94-AX94 -> 0
A95: 88 | B95: 292213 | C95: Tinta o almohadilla para sellos de radicación trámite de documentos | D95: NA | E95: NA | F95: NA | G95: 30 | H95: 6722.69 | I95: 0 | J95: {=IF($V95="","",IFERROR(INDEX(Articulacion!G:G,$V95),0))} | K95: {=IF($V95="","",IFERROR(INDEX(Articulacion!H:H,$V95),0))} | L95: {=IF($V95="","",IFERROR(INDEX(Articulacion!I:I,$V95),0))} | M95: {=IF($V95="","",IFERROR(INDEX(Articulacion!J:J,$V95),0))} | N95: {=IF($V95="","",IFERROR(INDEX(Articulacion!K:K,$V95),0))} | O95: {=IF($V95="","",IFERROR(INDEX(Articulacion!L:L,$V95),0))} | P95: {=IF($V95="","",IFERROR(INDEX(Articulacion!M:M,$V95),0))} | Q95: {=IF($V95="","",IFERROR(INDEX(Articulacion!N:N,$V95),0))} | R95: {=IF($V95="","",IFERROR(INDEX(Articulacion!O:O,$V95),0))} | S95: {=IF($V95="","",IFERROR(INDEX(Articulacion!P:P,$V95),0))} | T95: {=IF($V95="","",IFERROR(INDEX(Articulacion!Q:Q,$V95),0))} | U95: =IF($V95="",0,SUM(J95:T95)) -> 0 | W95: 15 | X95: 15 | AX95: =SUM(W95:AW95) -> 30 | AY95: =G95-U95-AX95 -> 0
A96: 1 | B96: 238187 | C96: Vinilo, pintura escolar colores surtidos, envase plástico con tapa dosificadora. 1000 ml pinturas a base de agua de secado rápido, buen poder de cubrimiento, colores entre mezclables de alta Unidad 19 intensidad. Contenido por frasco 1 litro (amarillo, azul, rojo, verde, naranja, blanco y negro) | D96: NA | E96: NA | F96: NA | G96: 15 | H96: 21008.4 | I96: 0 | J96: {=IF($V96="","",IFERROR(INDEX(Articulacion!G:G,$V96),0))} | K96: {=IF($V96="","",IFERROR(INDEX(Articulacion!H:H,$V96),0))} | L96: {=IF($V96="","",IFERROR(INDEX(Articulacion!I:I,$V96),0))} | M96: {=IF($V96="","",IFERROR(INDEX(Articulacion!J:J,$V96),0))} | N96: {=IF($V96="","",IFERROR(INDEX(Articulacion!K:K,$V96),0))} | O96: {=IF($V96="","",IFERROR(INDEX(Articulacion!L:L,$V96),0))} | P96: {=IF($V96="","",IFERROR(INDEX(Articulacion!M:M,$V96),0))} | Q96: {=IF($V96="","",IFERROR(INDEX(Articulacion!N:N,$V96),0))} | R96: {=IF($V96="","",IFERROR(INDEX(Articulacion!O:O,$V96),0))} | S96: {=IF($V96="","",IFERROR(INDEX(Articulacion!P:P,$V96),0))} | T96: {=IF($V96="","",IFERROR(INDEX(Articulacion!Q:Q,$V96),0))} | U96: =IF($V96="",0,SUM(J96:T96)) -> 0 | AJ96: 1 | AK96: 1 | AL96: 1 | AM96: 1 | AN96: 2 | AO96: 1 | AP96: 1 | AQ96: 1 | AR96: 1 | AS96: 1 | AT96: 1 | AU96: 1 | AV96: 1 | AW96: 1 | AX96: =SUM(W96:AW96) -> 15 | AY96: =G96-U96-AX96 -> 0
W97: =SUM(W3:W96) -> 103 | X97: =SUM(X3:X96) -> 104 | Y97: =SUM(Y3:Y96) -> 36 | Z97: =SUM(Z3:Z96) -> 34 | AA97: =SUM(AA3:AA96) -> 33 | AB97: =SUM(AB3:AB96) -> 33 | AC97: =SUM(AC3:AC96) -> 33 | AD97: =SUM(AD3:AD96) -> 32 | ... AX97: =SUM(AX3:AX96) -> 942 | AY97: =G97-U97-AX97 -> -942
W98: 103 | X98: 104 | Y98: 36 | Z98: 34 | AA98: 33 | AB98: 33 | AC98: 33 | AD98: 32 | AE98: 31 | AF98: 31 | AG98: 24 | AH98: 24 | AI98: 27 | AJ98: 29 | AK98: 28 | AL98: 26 | AM98: 27 | AN98: 54 | AO98: 27 | AP98: 23 | AQ98: 51 | AR98: 45 | AS98: 22 | AT98: 19 | AU98: 17 | AV98: 16 | AW98: 13 | AX98: =SUM(W98:AW98) -> 942 | AY98: =G98-U98-AX98 -> -942
W100: =W97-W98 -> 0 | X100: =X97-X98 -> 0 | Y100: =Y97-Y98 -> 0 | Z100: =Z97-Z98 -> 0 | AA100: =AA97-AA98 -> 0 | AB100: =AB97-AB98 -> 0 | AC100: =AC97-AC98 -> 0 | AD100: =AD97-AD98 -> 0 | ... AW100: =AW97-AW98 -> 0

Sheet Articulacion
A1: LINEA | B1: CONSECUTIVO | C1: CODIGO | D1: OBSERVACIONES | E1: CANTIDAD TOTAL | F1: ARTICULACION | G1: 3425230 ASISTENCIA ADMINISTRATIVA | H1: 3425227 ASISTENCIA ADMINISTRATIVA | I1: 3425495 ASISTENCIA ADMINISTRATIVA | J1: 3425231 CONTABILIZACION DE OPERACIONES COMERCIALES Y FINANCIERAS | K1: 3425503 CONTABILIZACION DE OPERACIONES COMERCIALES Y FINANCIERAS | L1: 3425505 CONTABILIZACION DE OPERACIONES COMERCIALES Y FINANCIERAS | M1: 3425511 VENTA DE PRODUCTOS EN LINEA | N1: 3425209 CONSERVACION DE RECURSOS NATURALES | O1: 3425210 CONSERVACION DE RECURSOS NATURALES | P1: 3425504 CONSERVACION DE RECURSOS NATURALES | Q1: 3425222 MONITOREO AMBIENTAL | R1: Total materiales
B2: 1 | C2: 60105410 | D2: Billetes y monedas didácticos pesos colombianos, impresos a color por ambos lados denominaciones $1000, $2000, $5000, $10.000, $20.000, $50.000 y $100.000. Medidas aproximadas 12 cm x 7 cm. Incluye 94 unidades de billetes surtidos y 80 unidades de monedas de cartón surtidas. | E2: 20 | F2: 8 | J2: 2 | K2: 2 | L2: 2 | M2: 2 | R2: =SUM(G2:Q2) -> 8
B3: 2 | C3: 44122003 | D3: Carpeta Blanca cuatro (4) aletas, Con una cubierta anterior y una posterior con solapas laterales que doblan al interior. Incluye grafado para 4 pliegues sobre cada solapa. La distancia entre los pliegues es de 1 cm., para obtener diferentes capacidades de almacenamiento. Debe tener un acabado liso, suave, libre de partículas abrasivas u otras imperfecciones. Se recomienda el uso de propalcore desacidificada de mínimo 240 g/m2 o de propalcote de 300 g/m2 o 320 g/m2. Y que cumplan con las siguientes dimensiones., Solapas laterales: (4 aletas) Gramaje 320 Gr. Medidas: Ancho en totalidad 69.5 cm X largo 69,5 cm Base central: ancho 22 Cm X largo 37 cm Base aletas laterales: ancho 25 Cm X largo 35 cm. Base aletas superiores: ancho 22 Cm X largo 17 cm. Grafas (5) con capacidad de hasta 400 folios. Material: Cartulina libre de pulpas lignificadas o recicladas propalcote 320g, Rotuladas con logo del SENA y nombre del Centro (REGIONAL HUILA - Centro de Formación Agroindustrial La Angostura) 1 sola tinta. Recubrimiento: PH neutro o con reserva alcalina. | E3: 87 | F3: 7 | G3: 1 | H3: 1 | I3: 1 | J3: 1 | K3: 1 | L3: 1 | M3: 1 | R3: =SUM(G3:Q3) -> 7
B4: 3 | C4: 14111519 | D4: Cartulina 1/8 colores surtidos PAQUETE X 10 UNIDADES. colores de 85cmX25cm | E4: 8 | F4: 25 | G4: 4 | H4: 4 | I4: 4 | J4: 4 | K4: 4 | L4: 3 | M4: 2 | R4: =SUM(G4:Q4) -> 25
B5: 4 | C5: 42312009 | D5: Cosedora manual, de estructura íntegramente metálica (acero o aleaciones resistentes) papel de hasta 30 hojas, de grapas estándar 26/6 | E5: 17 | F5: 2 | G5: 1 | M5: 1 | R5: =SUM(G5:Q5) -> 2
B6: 5 | C6: 44121708 | D6: Marcador Punta fina Negro Caja x 14 unidades Marcadores permanentes. Marca en: papel, plástico, metal y en la mayoría de las superficies. Colores intensos. Tinta que seca rápidamente, resistente a la decoloración y agua. | E6: 9 | F6: 1 | I6: 1 | R6: =SUM(G6:Q6) -> 1
B7: 6 | C7: 44121708 | D7: MARCADORES PERMANENTES, colores surtidos, caja x 10 unidades. para uso permanente de secado rápido casi sin olor y resistente al agua, Punta resistente redonda | E7: 13 | F7: 3 | G7: 1 | L7: 1 | M7: 1 | R7: =SUM(G7:Q7) -> 3
B8: 7 | C8: 44121708 | D8: Marcador permanente Tinta negra, punta fina. Caja X 12 unidades. Cuerpo redondo, Punta fina, tinta color negro, Permanente | E8: 12 | F8: 2 | H8: 1 | I8: 1 | R8: =SUM(G8:Q8) -> 2
B9: 8 | C9: 14111506 | D9: Resma de Papel bond tamaño carta, de 500 hojas, Color blanco, 75 gr | E9: 13 | F9: 3 | G9: 1 | K9: 1 | M9: 1 | R9: =SUM(G9:Q9) -> 3
B10: 9 | C10: 60124504 | D10: Rompecabezas Fauna Silvestre 1000pz | E10: 4 | F10: 4 | N10: 1 | O10: 1 | P10: 1 | Q10: 1 | R10: =SUM(G10:Q10) -> 4
B11: 10 | C11: 14111821 | D11: Comprobante de ingreso talonario, x, 80, hojas | E11: 1 | F11: 1 | J11: 1 | R11: =SUM(G11:Q11) -> 1
B12: 11 | C12: 14111808 | D12: Formato pagare paquete x 80 unidades | E12: 1 | F12: 1 | K12: 1 | R12: =SUM(G12:Q12) -> 1
B13: 12 | C13: 14111810 | D13: Formato contrato a término indefinido, paquete, x 12, Unidades | E13: 3 | F13: 3 | G13: 1 | H13: 1 | I13: 1 | R13: =SUM(G13:Q13) -> 3
B14: 13 | C14: 14111810 | D14: Formato contrato civil, paquete, x 12, unds | E14: 2 | F14: 2 | G14: 1 | I14: 1 | R14: =SUM(G14:Q14) -> 2
B15: 14 | C15: 14111810 | D15: formato contrato de trabajo a término fijo, paquete, x 12 , Unds | E15: 3 | F15: 3 | G15: 1 | H15: 1 | I15: 1 | R15: =SUM(G15:Q15) -> 3
B16: 15 | C16: 60105306 | D16: Formato hoja de vida sencilla, paquete, x, 10 unidades | E16: 7 | F16: 7 | G16: 1 | H16: 1 | I16: 1 | M16: 4 | R16: =SUM(G16:Q16) -> 7
B17: 16 | C17: 14111804 | D17: Libreta facturas Libro, de facturas, 1/2, carta | E17: 4 | F17: 4 | J17: 2 | K17: 1 | L17: 1 | R17: =SUM(G17:Q17) -> 4
B18: 17 | C18: 44121701 | D18: Lapicero Retráctil, de alta calidad, Tinta negra, Cuerpo en acrílico denso, Presentación: Caja x 12 unidades | E18: 5 | F18: 5 | G18: 1 | H18: 1 | J18: 1 | K18: 1 | M18: 1 | R18: =SUM(G18:Q18) -> 5
E19: =SUM(E2:E18) -> 209 | F19: =SUM(F2:F18) -> 81 | R19: =SUM(R2:R18) -> 81
